Workbook

Sheet articles_2026_01_26
A1: rayyan_key | B1: title | C1: year | D1: month | E1: day | F1: journal | G1: issn | H1: volume | I1: issue | J1: pages | K1: authors | L1: url | M1: language | N1: publisher | O1: location | P1: abstract | Q1: notes | R1: doi | S1: keywords | T1: pubmed_id | U1: pmc_id
A2: rayyan-83177405 | B2: Collaborative Adaptive Rangeland Management Fosters Management-Science Partnerships | C2: 2018 | F2: Rangeland Ecology & Management | G2: 1550-7424 | H2: 71 | I2: 5 | J2: 646-657 | K2: Wilmer H and Derner J D and Fernandez-Gimenez M E and Briske D D and Augustine D J and Porensky L M and Grp Carm Stakeholder | L2: <Go to ISI>://WOS:000446859300014 | Q2: Wilmer, Hailey Derner, Justin D. Fernandez-Gimenez, Maria E. Briske, David D. Augustine, David J. Porensky, Lauren M. Augustine, David/0000-0003-3144-0466; Derner, Justin/0000-0001-8076-0736; Fernandez-Gimenez, Maria/0000-0001-9641-1434 1551-5028 | RAYYAN-INCLUSION: {"Philip"=>"Excluded", "fereshteh"=>"Excluded", "Iris"=>"Included", "Sarah"=>"Included", "Nibedita"=>"Maybe", "Alec"=>"Included", "Alvaro"=>"Included"} | R2: 10.1016/j.rama.2017.07.008 | S2: eppi-reviewer
A3: rayyan-83177406 | B3: Entomological Society of America and Science Policy Engagement | C3: 2019 | F3: Annals of the Entomological Society of America | H3: 112 | I3: 2 | J3: 62-70 | K3: Wiedenmann Robert N and Zalom Frank G and Cadwalader Erin L and Alleyne Marianne and Stelzig Chris J | L3: http://0-search.ebscohost.com.catalogue.libraries.london.ac.uk/login.aspx?direct=true&db=a9h&AN=135201611&site=ehost-live | Q3: Wiedenmann, Robert N 1; Email Address: rwieden@uark.edu Zalom, Frank G 2 Cadwalader, Erin L 3 Alleyne, Marianne 4 Stelzig, Chris J 5; Affiliation: 1: Department of Entomology, University of Arkansas, Fayetteville, AR 2: Department of Entomology and Nematology, University of California, Davis, CA 3: Lewis-Burke Associates LLC, Washington, DC 4: Department of Entomology, University of Illinois, Urbana, IL 5: Entomological Society of America, Annapolis, MD; Source Info: Mar2019, Vol. 112 Issue 2, p62; Subject Term: ENTOMOLOGISTS; Subject Term: ENTOMOLOGY; Subject Term: SCIENCE &amp; state; Author-Supplied Keyword: Grand Challenges; Author-Supplied Keyword: policy fellows; Author-Supplied Keyword: science advocacy; Company/Entity: ENTOMOLOGICAL Society of America Company/Entity: UNITED States. Environmental Protection Agency; NAICS/Industry Codes: 541690 Other Scientific and Technical Consulting Services; NAICS/Industry Codes: 924110 Administration of Air and Water Resource and Solid Waste Management Programs; Number of Pages: 9p; Document Type: Article; Full Text Word Count: 8597 | RAYYAN-INCLUSION: {"Philip"=>"Excluded", "Nibedita"=>"Excluded", "Alec"=>"Excluded", "Alvaro"=>"Excluded"} | R3: 10.1093/aesa/say060 | S3: eppi-reviewer;ENTOMOLOGISTS ENTOMOLOGY SCIENCE &;tate Grand Challenge;policy fellow;cience advocacy ENTOMOLOGICAL Society of America UNITED State;Environmental Protection Agency
A4: rayyan-83177407 | B4: The need for transformative changes in the use of Indigenous knowledge along with science for environmental decision-making in the Arctic | C4: 2020 | F4: People and Nature | H4: 2 | I4: 3 | J4: 544-556 | K4: Wheeler H C and Danielsen F and Fidel M and Hausner V and Horstkotte T and Johnson N and Lee O and Mukherjee N and Amos A and Ashthorn H and Ballari O and Behe C and Breton-Honeyman K and Retter G B and Buschman V and Jakobsen P and Johnson F and Lyberth B and Parrott J A and Pogodaev M and Sulyandziga R and Vronski N | L4: <Go to ISI>://WOS:000647696100003 | Q4: Wheeler, Helen C. Danielsen, Finn Fidel, Maryann Hausner, Vera Horstkotte, Tim Johnson, Noor Lee, Olivia Mukherjee, Nibedita Amos, Amy Ashthorn, Heather Ballari, Oystein Behe, Carolina Breton-Honeyman, Kaitlin Retter, Gunn-Britt Buschman, Victoria Jakobsen, Paviarak Johnson, Frank Lyberth, Bjarne Parrott, Jennifer A. Pogodaev, Mikhail Sulyandziga, Rodion Vronski, Nikita Mukherjee, Nibedita/B-2531-2010 Mukherjee, Nibedita/0000-0002-2970-1498; Behe, Carolina/0000-0002-8141-8550; Hausner, Vera Helene/0000-0001-9825-0419; Wheeler, Helen/0000-0002-9820-5818 2575-8314 | RAYYAN-INCLUSION: {"Matthew"=>"Excluded", "Philip"=>"Excluded", "fereshteh"=>"Excluded", "Aidan"=>"Excluded", "Nibedita"=>"Included", "Alec"=>"Included", "Alvaro"=>"Excluded"} | R4: 10.1002/pan3.10131 | S4: eppi-reviewer
A5: rayyan-83177408 | B5: Increasing the uptake of ecological model results in policy decisions to improve biodiversity outcomes | C5: 2022 | F5: Environmental Modelling & Software | G5: 1364-8152 | H5: 149 | K5: Weiskopf S R and Harmackova Z V and Johnson C G and Londono-Murcia M C and Miller B W and Myers B J. E and Pereira L and Arce-Plata M I and Blanchard J L and Ferrier S and Fulton E A and Harfoot M and Isbell F and Johnson J A and Mori A S and Weng E S and Rosa I M. D | L5: <Go to ISI>://WOS:000787109500005 | Q5: Weiskopf, Sarah R. Harmackova, Zuzana, V Johnson, Ciara G. Londono-Murcia, Maria Cecilia Miller, Brian W. Myers, Bonnie J. E. Pereira, Laura Arce-Plata, Maria Isabel Blanchard, Julia L. Ferrier, Simon Fulton, Elizabeth A. Harfoot, Mike Isbell, Forest Johnson, Justin A. Mori, Akira S. Weng, Ensheng Rosa, Isabel M. D. Miller, Brian/0000-0003-1716-1161; Isbell, Forest/0000-0001-9689-769X; Weiskopf, Sarah/0000-0002-5933-8191 1873-6726 | RAYYAN-INCLUSION: {"Matthew"=>"Excluded", "Philip"=>"Included", "Alice"=>"Excluded", "Carlos"=>"Excluded", "Tabitha"=>"Included", "Prishnee"=>"Included", "Valentin"=>"Excluded", "Elina"=>"Included", "fereshteh"=>"Excluded", "Aidan"=>"Included", "Tiff"=>"Excluded", "Iris"=>"Included", "Sarah"=>"Excluded", "Nibedita"=>"Included", "Alec"=>"Excluded", "Alvaro"=>"Excluded", "Isobel"=>"Included"} | R5: 10.1016/j.envsoft.2022.105318 | S5: eppi-reviewer
A6: rayyan-83177409 | B6: Blueprints of Effective Biodiversity and Conservation Knowledge Products That Support Marine Policy | C6: 2017 | F6: Frontiers in Marine Science | H6: 4 | K6: Weatherdon L V and Appeltans W and Bowles-Newark N and Brooks T M and Davis F E and Despot-Belmonte K and Fletcher S and Garilao C and Hilton-Taylor C and Hirsch T and Juffe-Bignoli D and Kaschner K and Kingston N and Malsch K and Regan E C and Kesner-Reyes K and Rose D C and Wetzel F T and Wilkinson T and Martin C S | L6: <Go to ISI>://WOS:000457690600096 | Q6: Weatherdon, Lauren V. Appeltans, Ward Bowles-Newark, Nadine Brooks, Thomas M. Davis, Frances E. Despot-Belmonte, Katherine Fletcher, Stephen Garilao, Cristina Hilton-Taylor, Craig Hirsch, Tim Juffe-Bignoli, Diego Kaschner, Kristin Kingston, Naomi Malsch, Kelly Regan, Eugenie C. Kesner-Reyes, Kathleen Rose, David C. Wetzel, Florian T. Wilkinson, Tim Martin, Corinne S. ; Martin, Corinne/G-9041-2011 Weatherdon, Lauren V./0000-0002-3989-027X; Rose, David/0000-0002-5249-9021; Hirsch, Tim/0000-0002-5015-5807; Fletcher, Stephen/0000-0003-1180-9844; Martin, Corinne/0000-0002-5428-2766; Kaschner, Kristin/0000-0002-4061-626X 2296-7745 | RAYYAN-INCLUSION: {"Matthew"=>"Excluded", "Philip"=>"Excluded", "Alice"=>"Excluded", "Carlos"=>"Excluded", "Tabitha"=>"Excluded", "Prishnee"=>"Excluded", "Valentin"=>"Excluded", "Elina"=>"Excluded", "fereshteh"=>"Included", "Aidan"=>"Excluded", "Tiff"=>"Included", "Iris"=>"Excluded", "Sarah"=>"Excluded", "Nibedita"=>"Excluded", "Alec"=>"Excluded", "Isobel"=>"Excluded"} | R6: 10.3389/fmars.2017.00096 | S6: eppi-reviewer
A7: rayyan-83177410 | B7: EKLIPSE: engaging knowledge holders and networks for evidence-informed European policy on biodiversity and ecosystem services | C7: 2019 | F7: Evidence & Policy | G7: 1744-2648 | H7: 15 | I7: 2 | J7: 253-264 | K7: Watt A and Ainsworth G and Balian E and Cojocaru G and Darbi M and Dicks L and Eggermont H and Furman E and Goudeseune L and Huybrecht P and Kelemen E and Koch F and Konstantinou Z and Livoreil B and Locher K and Lux A and Mehring M and Nesshoever C and Paloniemi R and Saarikoski H and Pinto I S and Vandewalle M and Varjopuro R and Varumo L and Wittmer H and Young J | L7: <Go to ISI>://WOS:000471772800006 | Q7: Watt, Allan Ainsworth, Gill Balian, Estelle Cojocaru, George Darbi, Marianne Dicks, Lynn Eggermont, Hilde Furman, Eeva Goudeseune, Lise Huybrecht, Pierre Kelemen, Eszter Koch, Florian Konstantinou, Zoi Livoreil, Barbara Locher, Karla Lux, Alexandra Mehring, Marion Nesshoever, Carsten Paloniemi, Riikka Saarikoski, Heti Pinto, Isabel Sousa Vandewalle, Marie Varjopuro, Riku Varumo, Liisa Wittmer, Heidi Young, Juliette Pinto, Isabel Sousa/W-1591-2019; Wittmer, Heidi/H-7264-2012; Dicks, Lynn/AFH-5289-2022; Young, Juliette/B-4225-2012; Koch, Florian/F-2504-2015; Ainsworth, Gill/P-3013-2019 Pinto, Isabel Sousa/0000-0002-9231-0553; Wittmer, Heidi/0000-0001-6966-7258; Young, Juliette/0000-0002-8522-0883; Koch, Florian/0000-0002-0343-0730; Ainsworth, Gill/0000-0003-0460-6563; Goudeseune, Lise/0000-0002-4239-3338; Lux, Alexandra/0000-0002-6626-7977; Vandewalle, Marie/0000-0003-3619-9763; Cojocaru, George/0000-0002-1432-364X; Dicks, Lynn/0000-0002-8304-4468 1744-2656 | RAYYAN-INCLUSION: {"Matthew"=>"Excluded", "Philip"=>"Excluded", "Alice"=>"Excluded", "Carlos"=>"Excluded", "Tabitha"=>"Excluded", "Prishnee"=>"Excluded", "Valentin"=>"Excluded", "Elina"=>"Excluded", "fereshteh"=>"Included", "Aidan"=>"Excluded", "Tiff"=>"Excluded", "Iris"=>"Excluded", "Sarah"=>"Excluded", "Nibedita"=>"Excluded", "Alec"=>"Excluded", "Isobel"=>"Excluded"} | R7: 10.1332/174426418x15314036194114 | S7: eppi-reviewer
A8: rayyan-83177411 | B8: Characteristics of participatory monitoring projects and their relationship to decision-making in biological resource management: a review | C8: 2016 | F8: Biodiversity and Conservation | G8: 0960-3115 | H8: 25 | I8: 11 | J8: 2001-2019 | K8: Villasenor E and Porter-Bolland L and Escobar F and Guariguata M R and Moreno-Casasola P | L8: <Go to ISI>://WOS:000382014400001 | Q8: Villasenor, Emma Porter-Bolland, Luciana Escobar, Federico Guariguata, Manuel R. Moreno-Casasola, Patricia VILLASEÃ‘OR, EMMA/AAR-7143-2021; Escobar, Federico/C-1396-2011; Porter-Bolland, Luciana/C-1398-2016; Moreno-Casasola, Patricia/R-8562-2018; Bolland, Luciana Porter/AAH-4895-2020 Escobar, Federico/0000-0003-0179-7528; Porter-Bolland, Luciana/0000-0001-8586-3267; Moreno-Casasola, Patricia/0000-0003-0468-0851; Bolland, Luciana Porter/0000-0001-8586-3267 1572-9710 | RAYYAN-INCLUSION: {"Philip"=>"Excluded", "fereshteh"=>"Excluded", "Sarah"=>"Excluded", "Nibedita"=>"Excluded", "Alec"=>"Excluded"} | R8: 10.1007/s10531-016-1184-9 | S8: eppi-reviewer
A9: rayyan-83177413 | B9: What do scientists and managers know about soil biodiversity? Comparative knowledge mapping for sustainable forest management | C9: 2020 | F9: Forest Policy and Economics | G9: 1389-9341 | H9: 119 | K9: Vanermen I and Muys B and Verheyen K and Vanwindekens F and Bouriaud L and Kardol P and Vranken L | L9: <Go to ISI>://WOS:000568682900010 | Q9: Vanermen, Iris Muys, Bart Verheyen, Kris Vanwindekens, Frederic Bouriaud, Laura Kardol, Paul Vranken, Liesbet Kardol, Paul/N-8383-2015; Vranken, Liesbet/Q-1710-2018; BITOUN, RACHEL/AAC-9538-2021; Muys, Bart/A-3194-2015 Kardol, Paul/0000-0001-7065-3435; Vranken, Liesbet/0000-0003-1170-1139; Muys, Bart/0000-0001-9421-527X; Vanwindekens, Frederic/0000-0002-9117-7543 1872-7050 | RAYYAN-INCLUSION: {"Philip"=>"Excluded", "Alice"=>"Excluded", "fereshteh"=>"Excluded", "Nibedita"=>"Excluded", "Alec"=>"Excluded"} | R9: 10.1016/j.forpol.2020.102264 | S9: eppi-reviewer
A10: rayyan-83177414 | B10: A question of dissemination: Assessing the practices and implications of research in tropical landscapes | C10: 2019 | F10: AMBIO - A Journal of the Human Environment | H10: 48 | I10: 1 | J10: 35-47 | K10: Toomey Anne H and Alvaro MarÃ­a Eugenia Copa and Aiello-Lammens Matthew and Loayza Cossio and Oscar and Barlow Jos | L10: http://0-search.ebscohost.com.catalogue.libraries.london.ac.uk/login.aspx?direct=true&db=a9h&AN=133611999&site=ehost-live | Q10: Toomey, Anne H. 1; Email Address: atoomey@pace.edu Alvaro, MarÃ­a Eugenia Copa 2 Aiello-Lammens, Matthew 1 Loayza Cossio, Oscar 3 Barlow, Jos 4; Affiliation: 1: Department of Environmental Studies and Science, Pace University, 41 Park Row, #721B, 10038, New York, NY, USA 2: ColecciÃ³n Boliviana de Fauna, Calle 26 de Cota Cota (Ovidio SuÃ¡rez) Casilla NÂº 8706, La Paz, Bolivia 3: Madidi-Tambopata Landscape Conservation Program, Wildlife Conservation Society, Casilla 3-35Â 181 SM, La Paz, Bolivia 4: Lancaster Environment Centre, Lancaster University, LA1 4YQ, Bailrigg, Lancashire, UK; Source Info: Jan2019, Vol. 48 Issue 1, p35; Subject Term: SCIENTIFIC knowledge; Subject Term: CONSERVATIONISTS; Subject Term: ENVIRONMENTAL management; Subject Term: UNIVERSITIES &amp; colleges; Subject Term: PARQUE Nacional Madidi (Bolivia); Author-Supplied Keyword: Conservation management; Author-Supplied Keyword: Knowledge exchange; Author-Supplied Keyword: Local perceptions; Author-Supplied Keyword: Research ethics; Author-Supplied Keyword: Research-action; Author-Supplied Keyword: Research-implementation; NAICS/Industry Codes: 611310 Colleges, Universities, and Professional Schools; Number of Pages: 13p; Document Type: Article; Full Text Word Count: 7345 | RAYYAN-INCLUSION: {"Philip"=>"Included", "Tabitha"=>"Included", "fereshteh"=>"Excluded", "Iris"=>"Included", "Alec"=>"Included"} | R10: 10.1007/s13280-018-1056-5 | S10: eppi-reviewer;SCIENTIFIC knowledge CONSERVATIONISTS ENVIRONMENTAL management UNIVERSITIES & college;PARQUE Nacional Madidi (Bolivia) Con;ervation management Knowledge exchange Local perception;Re;earch ethic;earch-action Re;earch-implementation
A11: rayyan-83177415 | B11: lEvaluating the outcomes and processes of a research-action partnership: The need for continuous reflective evaluation | C11: 2016 | F11: Bothalia | G11: 0006-8241 | H11: 46 | I11: 2 | K11: Taylor C and Cockburn J and Rouget M and Ray-Mukherjee J and Mukherjee S and Slotow R and Roberts D and Boon R and O'Donoghue S and Douwes E | L11: <Go to ISI>://WOS:000389715000011 | Q11: Taylor, Chantal Cockburn, Jessica Rouget, Mathieu Ray-Mukherjee, Jayanti Mukherjee, Shomen Slotow, Rob Roberts, Debra Boon, Richard O'Donoghue, Sean Douwes, Errol Slotow, Rob/AAM-9053-2020 2311-9284 Si | RAYYAN-INCLUSION: {"Philip"=>"Included", "Tabitha"=>"Included", "fereshteh"=>"Excluded", "Alec"=>"Excluded"} | R11: 10.4102/abc.v46i2.2154 | S11: eppi-reviewer
A12: rayyan-83177416 | B12: Researchâ€“management partnerships: An opportunity to integrate genetics in conservation actions | C12: 2020 | F12: Conservation Science & Practice | H12: 2 | I12: 9 | J12: 46235 | K12: Taft Heather R and McCoskey Dana N and Miller Joshua M and Pearson Sarah K and Coleman Melinda A and Fletcher Nicholas K and Mittan Cinnamon S and Meek Mariah H and Barbosa Soraia | L12: http://0-search.ebscohost.com.catalogue.libraries.london.ac.uk/login.aspx?direct=true&db=a9h&AN=145430044&site=ehost-live | Q12: Taft, Heather R. 1 McCoskey, Dana N. 2 Miller, Joshua M. 3 Pearson, Sarah K. 4 Coleman, Melinda A. 5,6 Fletcher, Nicholas K. 7 Mittan, Cinnamon S. 7 Meek, Mariah H. 8 Barbosa, Soraia 9; Email Address: soraia.barbosa02@gmail.com; Affiliation: 1: Colorado State University Global, Aurora Colorado, USA 2: DC Audubon Society, Washington District of Columbia, USA 3: Department of Biological Sciences, University of Alberta, Edmonton Alberta,, Canada 4: College of Science and Engineering, Flinders University of South Australia, Adelaide South Australia,, Australia 5: Department of Primary Industries NSW Fisheries, National Marine Science Centre, Coffs Harbour New South Wales,, Australia 6: National Marine Science Centre, Southern Cross University, Coffs Harbour New South Wales,, Australia 7: Department of Ecology and Evolutionary Biology, Cornell University, Corson Hall, Ithaca New York, USA 8: Department of Integrative Biology, Michigan State University, East Lansing Michigan, USA 9: Department of Fish and Wildlife Sciences, University of Idaho, Moscow Idaho, USA; Source Info: Sep2020, Vol. 2 Issue 9, p1; Subject Term: CONSERVATION genetics; Subject Term: CONSERVATION biology; Subject Term: BUSINESS partnerships; Subject Term: DATA analysis; Subject Term: STRATEGIC planning; Author-Supplied Keyword: conservation genetics; Author-Supplied Keyword: management; Author-Supplied Keyword: partnerships; Author-Supplied Keyword: researchâ€implementation gap; Number of Pages: 8p; Document Type: Article; Full Text Word Count: 5054 | RAYYAN-INCLUSION: {"Matthew"=>"Included", "Philip"=>"Included", "Alice"=>"Excluded", "Carlos"=>"Included", "Tabitha"=>"Included", "Prishnee"=>"Included", "Valentin"=>"Included", "Elina"=>"Included", "fereshteh"=>"Excluded", "Aidan"=>"Included", "Tiff"=>"Included", "Iris"=>"Included", "Sarah"=>"Included", "Nibedita"=>"Included", "Alec"=>"Included", "Isobel"=>"Included"} | R12: 10.1111/csp2.218 | S12: eppi-reviewer;CONSERVATION genetic;CONSERVATION biology BUSINESS partner;hip;DATA analy;i;STRATEGIC planning management partner;re;earchâ€implementation gap
A13: rayyan-83177418 | B13: Challenges and opportunities of engaging biodiversity-related citizen science data in environmental decision-making: Practitioners' perceptions and a database analysis from Estonia | C13: 2021 | F13: Journal for Nature Conservation | G13: 1617-1381 | H13: 64 | K13: Suskevics M and Raadom T and Vanem B and Kana S and Roasto R and Runnel V and Kulvik M | L13: <Go to ISI>://WOS:000709046700010 | Q13: Suskevics, Monika Raadom, Terje Vanem, Brenda Kana, Silja Roasto, Reigo Runnel, Veljo Kulvik, Mart SuÅ¡keviÄs, Monika/H-3666-2017 SuÅ¡keviÄs, Monika/0000-0002-5666-2623 1618-1093 | RAYYAN-INCLUSION: {"Matthew"=>"Included", "Philip"=>"Included", "Alice"=>"Included", "Carlos"=>"Included", "Tabitha"=>"Included", "Prishnee"=>"Included", "Valentin"=>"Included", "Elina"=>"Included", "fereshteh"=>"Excluded", "Aidan"=>"Included", "Tiff"=>"Included", "Iris"=>"Included", "Sarah"=>"Included", "Nibedita"=>"Maybe", "Alec"=>"Included", "Isobel"=>"Included"} | R13: 10.1016/j.jnc.2021.126068 | S13: eppi-reviewer
A14: rayyan-83177420 | B14: Experiences from a National Landscape Monitoring ProgrammeMaintaining Continuity Whilst Meeting Changing Demands and Opportunities | C14: 2019 | F14: Land | H14: 8 | I14: 5 | K14: Stokstad G and Fjellstad W | L14: <Go to ISI>://WOS:000472659100005 | Q14: Stokstad, Grete Fjellstad, Wendy Fjellstad, Wendy/AAF-6257-2020 Fjellstad, Wendy Jane/0000-0002-2849-9785 2073-445x | RAYYAN-INCLUSION: {"Philip"=>"Excluded", "fereshteh"=>"Excluded", "Iris"=>"Included", "Alec"=>"Excluded"} | R14: 10.3390/land8050077 | S14: eppi-reviewer
A15: rayyan-83177421 | B15: Unblocking the flow of biodiversity data for decision-making in Africa | C15: 2017 | F15: Biological Conservation | H15: 213 | J15: 335-340 | K15: Stephenson P J and Bowles-Newark Nadine and Regan Eugenie and Stanwell-Smith Damon and Diagana MallÃ© and HÃ¶ft Robert and Abarchi Harouna and Abrahamse Tanya and Akello Christine and Allison Hilary and Banki Olaf and Batieno Barthelemy and Dieme Samuel and Domingos Arthur and Galt Russell and Githaiga Cicilia W and Guindo Abdoulaye Bine and Hafashimana David L N and Hirsch Tim and Hobern Donald | L15: http://0-search.ebscohost.com.catalogue.libraries.london.ac.uk/login.aspx?direct=true&db=a9h&AN=124610497&site=ehost-live | Q15: Stephenson, P.J. 1; Email Address: StephensonPJ@gmail.com Bowles-Newark, Nadine 2; Email Address: Nadine.Bowles-Newark@unep-wcmc.org Regan, Eugenie 2; Email Address: eugenie.regan@gmail.com Stanwell-Smith, Damon 2; Email Address: stanwellsmith@gmail.com Diagana, MallÃ© 3; Email Address: malle.diagana@iucn.org HÃ¶ft, Robert 4; Email Address: robert.hoft@cbd.int Abarchi, Harouna 5; Email Address: ab_harou@yahoo.fr Abrahamse, Tanya 6; Email Address: abrahamse@sanbi.org Akello, Christine 7; Email Address: cakelloechookit@yahoo.com Allison, Hilary 2; Email Address: Hilary.Allison@unep-wcmc.org Banki, Olaf 8; Email Address: Olaf@Banki.nl Batieno, Barthelemy 9; Email Address: barthelemy.batieno@iucn.org Dieme, Samuel 10; Email Address: sam_casa@yahoo.fr Domingos, Arthur 11; Email Address: aristofanesp@yahoo.com.br Galt, Russell 6; Email Address: R.Galt@sanbi.org.za Githaiga, Cicilia W. 12; Email Address: cgithaiga@nema.go.ke Guindo, Abdoulaye Bine 13; Email Address: abdoulayebine@yahoo.fr Hafashimana, David L.N. 7; Email Address: davidhaf2000@yahoo.com Hirsch, Tim 8; Email Address: thirsch@gbif.org Hobern, Donald 8; Email Address: dhobern@gbif.org; Affiliation: 1: WWF International, Gland, Switzerland 2: United Nations Environment Programme World Conservation Monitoring Centre (UNEP-WCMC), Cambridge, UK 3: WWF West Africa Marine Programme Office, Dakar, Senegal 4: Secretariat of the Convention on Biological Diversity, Montreal, Canada 5: Commission Technique sur la DiversitÃ© Biologique, Niamey, Niger 6: South African National Biodiversity Institute (SANBI), Pretoria, South Africa 7: National Environment Management Authority, Kampala, Uganda 8: Global Biodiversity Information Facility (GBIF), Copenhagen, Denmark 9: IUCN, Nouakchott, Mauritania 10: MinistÃ¨re de l'Environnement et de la Protection de la Nature, Dakar, Senegal 11: Ministry of Environment, Luanda, Angola 12: National Environment Management Authority, Nairobi, Kenya 13: MinistÃ¨re de l'Environnement, de l'Eau et de l'Assainissement, Bamako, Mali; Source Info: Sep2017 Part B, Vol. 213, p335; Subject Term: BIODIVERSITY conservation; Subject Term: DECISION making in environmental policy; Subject Term: ENVIRONMENTAL degradation; Subject Term: SUSTAINABLE development; Subject Term: GOVERNMENT agencies; Author-Supplied Keyword: Africa; Author-Supplied Keyword: Biodiversity; Author-Supplied Keyword: Data management; Author-Supplied Keyword: Environmental decision-making; NAICS/Industry Codes: 913910 Other local, municipal and regional public administration; NAICS/Industry Codes: 911910 Other federal government public administration; NAICS/Industry Codes: 912910 Other provincial and territorial public administration; NAICS/Industry Codes: 921190 Other General Government Support; NAICS/Industry Codes: 926110 Administration of General Economic Programs; Number of Pages: 6p; Document Type: Article | RAYYAN-INCLUSION: {"Matthew"=>"Included", "Philip"=>"Included", "Alice"=>"Included", "Carlos"=>"Included", "Tabitha"=>"Included", "Prishnee"=>"Included", "Valentin"=>"Included", "Elina"=>"Included", "fereshteh"=>"Excluded", "Aidan"=>"Included", "Tiff"=>"Included", "Iris"=>"Included", "Sarah"=>"Included", "Nibedita"=>"Included", "Alec"=>"Included", "Isobel"=>"Included"} | R15: 10.1016/j.biocon.2016.09.003 | S15: eppi-reviewer;BIODIVERSITY con;ervation DECISION making in environmental policy ENVIRONMENTAL degradation SUSTAINABLE developmen...;Africa Biodiver;ity Data management Environmental deci;ion-making
A16: rayyan-83177422 | B16: Exploring the usefulness of scenario archetypes in science-policy processes: experience across IPBES assessments | C16: 2019 | F16: Ecology and Society | G16: 1708-3087 | H16: 24 | I16: 3 | K16: Sitas N and Harmackova Z V and Anticamara J A and Arneth A and Badola R and Biggs R and Blanchard R and Brotons L and Cantele M and Coetzer K and DasGupta R and den Belder E and Ghosh S and Guisan A and Gundimeda H and Hamann M and Harrison P A and Hashimoto S and Hauck J and Klatt B J and Kok K and Krug R M and Niamir A and O'Farrell P J and Okayasu S and Palomo I and Pereira L M and Riordan P and Santos-Martin F and Selomane O and Shin Y J and Valle M | L16: <Go to ISI>://WOS:000490942000017 | Q16: Sitas, Nadia Harmackova, Zuzana V. Anticamara, Jonathan A. Arneth, Almut Badola, Ruchi Biggs, Reinette Blanchard, Ryan Brotons, Lluis Cantele, Matthew Coetzer, Kaera DasGupta, Rajarshi den Belder, Eefje Ghosh, Sonali Guisan, Antoine Gundimeda, Haripriya Hamann, Maike Harrison, Paula A. Hashimoto, Shizuka Hauck, Jennifer Klatt, Brian J. Kok, Kasper Krug, Rainer M. Niamir, Aidin O'Farrell, Patrick J. Okayasu, Sana Palomo, Ignacio Pereira, Laura M. Riordan, Philip Santos-Martin, Fernando Selomane, Odirilwe Shin, Yunne-Jai Valle, Mireia blanchard, ryan/B-8856-2017; Shin, Yunne-Jai/A-7575-2012; Guisan, Antoine/A-1057-2011; Dasgupta, Rajarshi/AAF-7822-2021; Niamir, Aidin/G-5779-2011; HASHIMOTO, Shizuka/P-5317-2019; Riordan, Philip/AAY-6420-2020; Arneth, Almut/B-2702-2013; DasGupta, Rajarshi/AAX-2695-2021; Pereira, Laura M./L-7258-2013; Biggs, Reinette/A-5155-2010; O'Farrell, Patrick/AAQ-7728-2021; Hauck, Jennifer/P-4115-2017; Selomane, Odirilwe/L-8068-2019; PALOMO, IGNACIO/D-4398-2014; HarmÃ¡ÄkovÃ¡, Zuzana V./G-1886-2014; Valle, Mireia/G-5783-2011 blanchard, ryan/0000-0002-3560-4133; Shin, Yunne-Jai/0000-0002-7259-9265; Guisan, Antoine/0000-0002-3998-4815; Niamir, Aidin/0000-0003-4511-3407; HASHIMOTO, Shizuka/0000-0003-4423-9374; Arneth, Almut/0000-0001-6616-0822; DasGupta, Rajarshi/0000-0003-0051-5090; Pereira, Laura M./0000-0002-4996-7234; Biggs, Reinette/0000-0003-0300-4149; O'Farrell, Patrick/0000-0002-9538-8831; Hauck, Jennifer/0000-0002-1614-9657; Selomane, Odirilwe/0000-0002-6892-4221; PALOMO, IGNACIO/0000-0002-4573-5989; HarmÃ¡ÄkovÃ¡, Zuzana V./0000-0001-7711-4135; Okayasu, Sana/0000-0002-6534-0458; Santos Martin, Fernando/0000-0002-2301-5876; Sitas, Nadia/0000-0003-0888-8617; Kok, Kasper/0000-0002-6319-9227; Riordan, Philip/0000-0001-6285-8596; Valle, Mireia/0000-0001-8517-8518 | RAYYAN-INCLUSION: {"Philip"=>"Included", "Alice"=>"Included", "fereshteh"=>"Included", "Alec"=>"Excluded"} | R16: 10.5751/es-11039-240335 | S16: eppi-reviewer
A17: rayyan-83177423 | B17: The role and value of science in shark conservation advocacy | C17: 2021 | F17: Scientific Reports | H17: 11 | I17: 1 | J17: 16626-16626 | K17: Shiffman D S and Macdonald C C and Wallace S S and Dulvy N K | L17: https://ovidsp.ovid.com/ovidweb.cgi?T=JS&CSC=Y&NEWS=N&PAGE=fulltext&D=med19&AN=34404844 https://discover.lshtm.ac.uk/openurl/44HYG/44HYG_services_page?sid=OVID:medline&id=doi:10.1038%2Fs41598-021-96020-4&id=pmid34404844&issn=2045-2322&isbn=&volume=11&issue=1&spage=16626&pages=16626&date=2021&title=Scientific+Reports&atitle=The+role+and+value+of+science+in+shark+conservation+advocacy.&aulast=Shiffman&pid=%3Cauthor%3EShiffman+DS%3BMacdonald+CC%3BWallace+SS%3BDulvy+NK%3C%2Fauthor%3E%3CAN%3E34404844 | O17: Shiffman, David S. Earth to Oceans Group, Department of Biological Sciences, Simon Fraser University | Q17: Shiffman, David S Macdonald, Catherine C Wallace, S Scott Dulvy, Nicholas K | RAYYAN-INCLUSION: {"Matthew"=>"Included", "Philip"=>"Included", "Alice"=>"Included", "Carlos"=>"Excluded", "Tabitha"=>"Excluded", "Prishnee"=>"Excluded", "Valentin"=>"Included", "Elina"=>"Excluded", "fereshteh"=>"Included", "Aidan"=>"Included", "Tiff"=>"Excluded", "Iris"=>"Excluded", "Sarah"=>"Included", "Nibedita"=>"Included", "Alec"=>"Included", "Isobel"=>"Included"} | S17: eppi-reviewer
A18: rayyan-83177424 | B18: Harnessing the Power of Community Science to Address Data Gaps in Arctic Observing: Invasive Species in Alaska as Case Examples | C18: 2021 | F18: Arctic Journal | H18: 74 | J18: 41640 | K18: Schwoerer Tobias and Spellman Katie V and Davis Tammy J and Lee Olivia and Martin Aaron and Mulder Christa P H and Swenson Nicole Y and Taylor Audrey and Winter Genelle | L18: http://0-search.ebscohost.com.catalogue.libraries.london.ac.uk/login.aspx?direct=true&db=a9h&AN=153358032&site=ehost-live | Q18: Schwoerer, Tobias 1; Email Address: tschwoerer@alaska.edu Spellman, Katie V. 1 Davis, Tammy J. 2 Lee, Olivia 1 Martin, Aaron 3 Mulder, Christa P. H. 4 Swenson, Nicole Y. 5 Taylor, Audrey 6 Winter, Genelle 7; Affiliation: 1: International Arctic Research Center, University of Alaska Fairbanks, 2160 North Koyukuk Drive, Fairbanks, Alaska 99775, USA 2: Alaska Department of Fish and Game, 1255 West 8th Street, Juneau, Alaska 99801, USA 3: U.S. Fish and Wildlife Service, 1011 East Tudor Road, Anchorage, Alaska 99503, USA 4: Institute of Arctic Biology and Department of Biology and Wildlife, University of Alaska Fairbanks, 2140 North Koyukuk Drive, Fairbanks, Alaska 99775, USA 5: Tyonek Tribal Conservation District, 1689 C Street, Suite 219, Anchorage, Alaska 99501, USA 6: Department of Biological Sciences, University of Alaska Anchorage, 3211 Providence Drive, Anchorage, Alaska 99508, USA 7: Metlakatla Indian Community, PO Box 8, Metlakatla, Alaska 99926, USA; Source Info: 2021 Supplement, Vol. 74, p1; Subject Term: INTRODUCED organisms; Subject Term: DATA science; Subject Term: COMMUNITY-based programs; Subject Term: CITIZEN science; Subject Term: BIOLOGICAL invasions; Subject Term: FOOD security; Subject Term: ECOSYSTEMS; Subject Term: ARCTIC regions; Subject Term: ALASKA; Author-Supplied Keyword: alien species; Author-Supplied Keyword: Arctic observing; Author-Supplied Keyword: citizen science; Author-Supplied Keyword: community science; Author-Supplied Keyword: early detection; Author-Supplied Keyword: evidence-based policy; Author-Supplied Keyword: monitoring; Author-Supplied Keyword: dÃ©tection prÃ©coce; Author-Supplied Keyword: espÃ¨ces Ã©trangÃ¨res; Author-Supplied Keyword: observation de l'Arctique; Author-Supplied Keyword: politique fondÃ©e sur des donnÃ©es probantes; Author-Supplied Keyword: science citoyenne; Author-Supplied Keyword: science communautaire; Author-Supplied Keyword: surveillance; Language of Keywords: English; Language of Keywords: French; Number of Pages: 14p; Document Type: Article | RAYYAN-INCLUSION: {"Philip"=>"Excluded", "fereshteh"=>"Included", "Aidan"=>"Excluded", "Alec"=>"Excluded"} | R18: 10.14430/arctic73773 | S18: eppi-reviewer;INTRODUCED organi;m;DATA;cience COMMUNITY-ba;ed program;CITIZEN;cience BIOLOGICAL inva;ion;FOOD;ecurity ECOSYSTEMS ARCTIC region;ALASKA alien;pecie;Arctic ob;erving community;cience early detection evidence-ba;ed policy monitoring dÃ©tection prÃ©coce e;pÃ¨ce;Ã©trangÃ¨re;ob;ervation de l'Arctique politique fondÃ©e;ur de;donnÃ©e;probante;cience citoyenne;cience communautaire;urveillance
A19: rayyan-83177427 | B19: Adopting Citizen Science as a Tool to Enhance Monitoring for an Environment Agency | C19: 2019 | F19: Citizen Science: Theory & Practice | H19: 6 | I19: 1 | J19: 46266 | K19: Roger Erin and Turak Eren and Tegart Patrick | L19: http://0-search.ebscohost.com.catalogue.libraries.london.ac.uk/login.aspx?direct=true&db=a9h&AN=140757826&site=ehost-live | Q19: Roger, Erin 1; Email Address: erin.roger@csiro.au Turak, Eren 1 Tegart, Patrick 1; Affiliation: 1: NSW Office of Environment and Heritage, AU; Source Info: 2019, Vol. 6 Issue 1, p1; Subject Term: CITIZEN science; Subject Term: ACQUISITION of data; Subject Term: DECISION making; Subject Term: PILOT projects; Subject Term: COMMUNITY involvement; Author-Supplied Keyword: barriers; Author-Supplied Keyword: citizen science; Author-Supplied Keyword: decision-making; Author-Supplied Keyword: government; Author-Supplied Keyword: strategy; Number of Pages: 9p; Document Type: Article | RAYYAN-INCLUSION: {"Philip"=>"Excluded", "Elina"=>"Excluded", "fereshteh"=>"Included", "Alec"=>"Excluded"} | R19: 10.5334/cstp.231 | S19: eppi-reviewer;CITIZEN;cience ACQUISITION of data DECISION making PILOT project;COMMUNITY involvement barrier;deci;ion-making government;trategy
A20: rayyan-83177428 | B20: Boundary Work: Engaging Knowledge Systems in Co-management of Feral Animals on Indigenous Lands | C20: 2012 | F20: Ecology & Society | H20: 17 | I20: 2 | J20: 387-399 | K20: Robinson Catherine J and Wallington Tabatha J | L20: http://0-search.ebscohost.com.catalogue.libraries.london.ac.uk/login.aspx?direct=true&db=a9h&AN=77928781&site=ehost-live | Q20: Robinson, Catherine J. 1 Wallington, Tabatha J. 1; Affiliation: 1: CSIRO Ecosystem Sciences; Source Info: 2012, Vol. 17 Issue 2, p387; Subject Term: FERAL animals; Subject Term: WILDLIFE conservation; Subject Term: TRADITIONAL ecological knowledge; Subject Term: ENVIRONMENTAL management; Subject Term: ENVIRONMENTAL protection; Subject Term: AUSTRALIA; Author-Supplied Keyword: co-benefits; Author-Supplied Keyword: co-managed boundary work; Author-Supplied Keyword: collaboration; Author-Supplied Keyword: environmental governance; Author-Supplied Keyword: feral animal management; Author-Supplied Keyword: Indigenous knowledge; Author-Supplied Keyword: knowledge-action systems; Number of Pages: 12p; Document Type: Article | RAYYAN-INCLUSION: {"Philip"=>"Excluded", "fereshteh"=>"Excluded", "Iris"=>"Included", "Alec"=>"Included"} | R20: 10.5751/ES-04836-170216 | S20: eppi-reviewer;FERAL animal;WILDLIFE con;ervation TRADITIONAL ecological knowledge ENVIRONMENTAL management ENVIRONMENTAL protection AUSTR...;co-managed boundary work collaboration environmental governance feral animal management Indigenou;knowledge knowledge-action;y;tem
A21: rayyan-83177429 | B21: Social process in grizzly bear management: lessons for collaborative governance and natural resource policy | C21: 2012 | F21: Policy Sciences | G21: 322687 | H21: 45 | I21: 3 | J21: 265-291 | K21: Richie Lauren and Oppenheimer J Daniel and Clark Susan G | L21: https://www.proquest.com/scholarly-journals/social-process-grizzly-bear-management-lessons/docview/1030728772/se-2?accountid=14511 https://ucl-new-primo.hosted.exlibrisgroup.com/openurl/UCL/UCL_VU2?url_ver=Z39.88-2004&rft_val_fmt=info:ofi/fmt:kev:mtx:journal&genre=article&sid=ProQ:ProQ%3Aibss&atitle=Social+process+in+grizzly+bear+management%3A+lessons+for+collaborative+governance+and+natural+resource+policy&title=Policy+Sciences&issn=00322687&date=2012-09-01&volume=45&issue=3&spage=265&au=Richi | Q21: Copyright - Springer Science+Business Media, LLC. 2012 CODEN - PLSCBZ SubjectsTermNotLitGenreText - Canada | RAYYAN-INCLUSION: {"Philip"=>"Excluded", "fereshteh"=>"Excluded", "Sarah"=>"Included", "Alec"=>"Included"} | R21: https://doi.org/10.1007/s11077-012-9160-z | S21: eppi-reviewer;Political Science;Natural resource management;Bears;Public policy;Analysis;Studies;Collaboration;National parks;Decision making;Canada;71219:Nature Parks and Other Similar Institutions;2600:Management science/operations research;9130:Experimental/theoretical;9172:Canada;1200:Social policy;1530:Natural resources
A22: rayyan-83177433 | B22: Evidence-informed policy and practice: The role and potential of civil society | C22: 2020 | F22: African Evaluation Journal | H22: 8 | I22: 1 | J22: 46327 | K22: Pabari Mine and Amisi Matodzi M and David-Gnahoui Emmanuel and Bedu-Addo Dede and Goldman Ian | L22: http://0-search.ebscohost.com.catalogue.libraries.london.ac.uk/login.aspx?direct=true&db=a9h&AN=148228034&site=ehost-live | Q22: Pabari, Mine 1; Email Address: mine.pabari@athariadvisory.co.ke Amisi, Matodzi M. 1 David-Gnahoui, Emmanuel 2 Bedu-Addo, Dede 3 Goldman, Ian 1; Affiliation: 1: CLEAR Anglophone Africa (CLEAR AA), Faculty of Commerce, Law and Management, University of the Witwatersrand, Johannesburg, South Africa 2: Faculty of Human and Social Sciences, University of Abomey-Calavi, Cotonou, Benin 3: Ghana Monitoring and Evaluation Forum (GMEF), Accra, Ghana; Source Info: 2020, Vol. 8 Issue 1, p1; Subject Term: CIVIL society; Subject Term: VIOLENCE against women; Subject Term: BEHAVIOR; Subject Term: CASE studies; Subject Term: BENIN; Subject Term: GHANA; Subject Term: KENYA; Author-Supplied Keyword: Citizen engagement; Author-Supplied Keyword: Civil society; Author-Supplied Keyword: Evidence use; Author-Supplied Keyword: Evidence-informed policymaking; Author-Supplied Keyword: Sustainable development; Number of Pages: 11p; Document Type: Article | RAYYAN-INCLUSION: {"Philip"=>"Excluded", "fereshteh"=>"Excluded", "Aidan"=>"Excluded", "Alec"=>"Included"} | R22: 10.4102/aej.v8i1.470 | S22: eppi-reviewer;CIVIL;ociety VIOLENCE again;t women BEHAVIOR CASE;tudie;BENIN GHANA KENYA Citizen engagement Evidence u;e Evidence-informed policymaking Su;tainable development
A23: rayyan-83177435 | B23: Pathways to impact for aquatic conservation science via multi-modal communication and stakeholder engagement | C23: 2020 | F23: Aquatic Conservation-Marine and Freshwater Ecosystems | G23: 1052-7613 | H23: 30 | I23: 9 | J23: 1791-1797 | K23: Noble M M and Fulton C J | L23: <Go to ISI>://WOS:000570237100014 | Q23: Noble, Mae M. Fulton, Christopher J. Fulton, Christopher J/A-5971-2008 Fulton, Christopher J/0000-0002-1140-1999 1099-0755 Si | RAYYAN-INCLUSION: {"Matthew"=>"Included", "Philip"=>"Included", "Alice"=>"Included", "Carlos"=>"Maybe", "Tabitha"=>"Included", "Prishnee"=>"Excluded", "Valentin"=>"Excluded", "Elina"=>"Included", "fereshteh"=>"Excluded", "Aidan"=>"Included", "Tiff"=>"Included", "Iris"=>"Included", "Sarah"=>"Included", "Nibedita"=>"Included", "Alec"=>"Included", "Isobel"=>"Included"} | R23: 10.1002/aqc.3380 | S23: eppi-reviewer
A24: rayyan-83177440 | B24: Use of web-based species occurrence information systems by academics and government professionals | C24: 2020 | F24: PLoS ONE [Electronic Resource] | H24: 15 | I24: 7 | J24: e0236556-e0236556 | K24: Martin-Mora E and Ellis S and Page L M | L24: https://ovidsp.ovid.com/ovidweb.cgi?T=JS&CSC=Y&NEWS=N&PAGE=fulltext&D=med18&AN=32735594 https://discover.lshtm.ac.uk/openurl/44HYG/44HYG_services_page?sid=OVID:medline&id=doi:10.1371%2Fjournal.pone.0236556&id=pmid32735594&issn=1932-6203&isbn=&volume=15&issue=7&spage=e0236556&pages=e0236556&date=2020&title=PLoS+ONE+%5BElectronic+Resource%5D&atitle=Use+of+web-based+species+occurrence+information+systems+by+academics+and+government+professionals.&aulast=Martin-Mora&pid=%3Cauthor%3EMartin-Mora+E%3BE | O24: Martin-Mora, Elizabeth. School of Natural Resources and Environment, University of Florida, Gainesvi | Q24: Martin-Mora, Elizabeth Ellis, Shari Page, Lawrence M | RAYYAN-INCLUSION: {"Matthew"=>"Included", "Philip"=>"Included", "Alice"=>"Included", "Carlos"=>"Excluded", "Tabitha"=>"Excluded", "Prishnee"=>"Excluded", "Valentin"=>"Included", "Elina"=>"Excluded", "fereshteh"=>"Excluded", "Aidan"=>"Included", "Tiff"=>"Excluded", "Iris"=>"Included", "Sarah"=>"Excluded", "Nibedita"=>"Excluded", "Alec"=>"Included", "Isobel"=>"Included"} | S24: eppi-reviewer
A25: rayyan-83177445 | B25: Stakeholder participation in IPBES: connecting local environmental work with global decision making | C25: 2020 | F25: Ecosystems and People | H25: 16 | I25: 1 | J25: 197-211 | K25: Krug Cornelia B and Sterling Eleanor and Cadman Timothy and Geschke Jonas and Drummond de Castro, Paula F and Schliep Rainer and Osemwegie Isimemen and Muller-Karger Frank E and Maraseni Tek | L25: https://ovidsp.ovid.com/ovidweb.cgi?T=JS&CSC=Y&NEWS=N&PAGE=fulltext&D=pmnm5&AN=32984823 https://discover.lshtm.ac.uk/openurl/44HYG/44HYG_services_page?sid=OVID:medline&id=doi:10.1080%2F26395916.2020.1788643&id=pmid32984823&issn=2639-5908&isbn=&volume=16&issue=1&spage=197&pages=197-211&date=2020&title=Ecosystems+and+People&atitle=Stakeholder+participation+in+IPBES%3A+connecting+local+environmental+work+with+global+decision+making.&aulast=Krug&pid=%3Cauthor%3EKrug+CB%3BSterling+E%3BCadman+T%3BGesc | O25: Krug, Cornelia B. bioDISCOVERY, Department of Geography, University of Zurich, Zurich, Switzerland. | Q25: Krug CB Sterling E Cadman T Geschke J Drummond de Castro PF Schliep R Osemwegie I Muller-Karger FE Maraseni T | RAYYAN-INCLUSION: {"Philip"=>"Excluded", "Carlos"=>"Included", "Elina"=>"Excluded", "fereshteh"=>"Included"} | S25: eppi-reviewer
A26: rayyan-83177449 | B26: Improving technical information use: what can be learnt from a manager's perspective? | C26: 2013 | F26: Environmental Management | H26: 52 | I26: 1 | J26: 221-233 | K26: Jacobson C and Lisle A and Carter R W and Hockings M T | L26: https://ovidsp.ovid.com/ovidweb.cgi?T=JS&CSC=Y&NEWS=N&PAGE=fulltext&D=med10&AN=23728487 https://discover.lshtm.ac.uk/openurl/44HYG/44HYG_services_page?sid=OVID:medline&id=doi:10.1007%2Fs00267-013-0084-y&id=pmid23728487&issn=0364-152X&isbn=&volume=52&issue=1&spage=221&pages=221-33&date=2013&title=Environmental+Management&atitle=Improving+technical+information+use%3A+what+can+be+learnt+from+a+manager%27s+perspective%3F.&aulast=Jacobson&pid=%3Cauthor%3EJacobson+C%3BLisle+A%3BCarter+RW%3BHockings+MT | O26: Jacobson, C. Sustainability Research Centre, University of the Sunshine Coast, Maroochydore DC, Lock | Q26: Jacobson, C Lisle, A Carter, R W Hockings, M T | RAYYAN-INCLUSION: {"Matthew"=>"Included", "Philip"=>"Included", "Alice"=>"Included", "Carlos"=>"Included", "Tabitha"=>"Included", "Prishnee"=>"Included", "Valentin"=>"Excluded", "Elina"=>"Included", "fereshteh"=>"Excluded", "Aidan"=>"Included", "Tiff"=>"Included", "Iris"=>"Included", "Sarah"=>"Included", "Nibedita"=>"Excluded", "Alec"=>"Included", "Isobel"=>"Included"} | S26: eppi-reviewer
A27: rayyan-83177453 | B27: Science Collaboration for Capacity Building: Advancing Technology Transfer Through a Treaty for Biodiversity Beyond National Jurisdiction | C27: 2020 | F27: Frontiers in Marine Science | H27: 7 | K27: Harden-Davies H and Snelgrove P | L27: <Go to ISI>://WOS:000517576400001 | Q27: Harden-Davies, Harriet Snelgrove, Paul Harden-Davies, Harriet/0000-0002-8214-5187 2296-7745 | RAYYAN-INCLUSION: {"Philip"=>"Excluded", "Carlos"=>"Excluded", "Elina"=>"Excluded", "fereshteh"=>"Included"} | R27: 10.3389/fmars.2020.00040 | S27: eppi-reviewer
A28: rayyan-83177455 | B28: The ecosystem approach as a framework for understanding knowledge utilisation | C28: 2014 | F28: ENVIRONMENT AND PLANNING C-GOVERNMENT AND POLICY | H28: 32 | I28: 2 | J28: 301-319 | K28: Haines-Young Roy and Potschin Marion | N28: SAGE PUBLICATIONS LTD | O28: 1 OLIVERS YARD, 55 CITY ROAD, LONDON EC1Y 1SP, ENGLAND | Q28: RAYYAN-INCLUSION: {"Philip"=>"Excluded", "Carlos"=>"Excluded", "fereshteh"=>"Excluded"} | R28: 10.1068/c1329j | S28: eppi-reviewer;eco;y;tem approach;knowledge utili;ation and inno
A29: rayyan-83177457 | B29: The role of boundary organizations in co-management: examining the politics of knowledge integration in a marine protected area in Belize | C29: 2016 | F29: International Journal of the Commons | G29: 1875-0281 | H29: 10 | I29: 2 | J29: 1013-1034 | K29: Gray N J | L29: <Go to ISI>://WOS:000388648200025 | Q29: Gray, Noella J. Annual Conference of the American-Anthropological-Association 2013 Chicago, IL Amer Anthropol Assoc | RAYYAN-INCLUSION: {"Matthew"=>"Included", "Philip"=>"Included", "fereshteh"=>"Included"} | R29: 10.18352/ijc.643 | S29: eppi-reviewer
A30: rayyan-83177458 | B30: Data selection for making biodiversity management decisions: Best available science and institutionalized agency norms | C30: 2013 | F30: Administration & Society | H30: 45 | I30: 2 | J30: 213-241 | K30: Gerlach John David and Williams Laron K and Forcina Colleen E | L30: https://ovidsp.ovid.com/ovidweb.cgi?T=JS&CSC=Y&NEWS=N&PAGE=fulltext&D=psyc10&AN=2013-15898-005 https://discover.lshtm.ac.uk/openurl/44HYG/44HYG_services_page?sid=OVID:psycdb&id=doi:10.1177%2F0095399712451886&id=pmid&issn=0095-3997&isbn=&volume=45&issue=2&spage=213&pages=213-241&date=2013&title=Administration+%26+Society&atitle=Data+selection+for+making+biodiversity+management+decisions%3A+Best+available+science+and+institutionalized+agency+norms.&aulast=Gerlach&pid=%3Cauthor%3EGerlach%2C+John+D | Q30: RAYYAN-INCLUSION: {"Philip"=>"Included", "Alice"=>"Included", "fereshteh"=>"Included"} | S30: eppi-reviewer
A31: rayyan-83177461 | B31: Exploring connections among the multiple outputs and outcomes emerging from 25 years of sea turtle conservation in Northern Cyprus | C31: 2020 | F31: Journal for Nature Conservation | G31: 1617-1381 | H31: 55 | K31: Edwards R C and Godley B J and Nuno A | L31: <Go to ISI>://WOS:000536928400016 | Q31: Edwards, Rachael C. Godley, Brendan J. Nuno, Ana Nuno, Ana/H-9497-2019 Nuno, Ana/0000-0003-4680-2378; Edwards, Rachael Catherine/0000-0003-4717-7615 1618-1093 | RAYYAN-INCLUSION: {"Matthew"=>"Included", "Philip"=>"Excluded", "fereshteh"=>"Included"} | R31: 10.1016/j.jnc.2020.125816 | S31: eppi-reviewer
A32: rayyan-83177462 | B32: Red lists in conservation science-policy interfaces: A case study from Vietnam | C32: 2018 | F32: Biological Conservation | H32: 226 | J32: 101-110 | K32: Do Thi Huong and Krott Max and Juerges Nataly and BÃ¶cher Michael | L32: http://0-search.ebscohost.com.catalogue.libraries.london.ac.uk/login.aspx?direct=true&db=a9h&AN=131628516&site=ehost-live | Q32: Do, Thi Huong 1; Email Address: dohuongnlkh@gmail.com Krott, Max 1 Juerges, Nataly 1 BÃ¶cher, Michael 1; Affiliation: 1: Chair Group of Forest and Nature Conservation Policy, George-August University of GÃ¶ttingen, BÃ¼sgenweg 3, 37077 GÃ¶ttingen, Germany; Source Info: Oct2018, Vol. 226, p101; Subject Term: ENDANGERED species; Subject Term: BIODIVERSITY conservation; Subject Term: KNOWLEDGE transfer; Subject Term: CONSERVATION biology; Author-Supplied Keyword: Biodiversity conservation; Author-Supplied Keyword: Red lists; Author-Supplied Keyword: RIU model; Author-Supplied Keyword: Scienceâ€“policy interface; Author-Supplied Keyword: Science-based policy advice; Author-Supplied Keyword: Vietnamese Red Data Book; Reviews &amp; Products: RED data book; Number of Pages: 10p; Document Type: Article | RAYYAN-INCLUSION: {"Philip"=>"Included", "fereshteh"=>"Included", "Nibedita"=>"Included"} | R32: 10.1016/j.biocon.2018.07.016 | S32: eppi-reviewer;ENDANGERED;pecie;BIODIVERSITY con;ervation KNOWLEDGE tran;fer CONSERVATION biology Red li;t;RIU model Scienceâ€“policy interface Science-ba;ed policy advice Vietname;e Red Data Book RED data book
A33: rayyan-83177463 | B33: Toward successful implementation of conservation research: A case study from Vietnam | C33: 2018 | F33: Ambio | H33: 47 | I33: 5 | J33: 608-621 | K33: Do Thi and H and Krott M and Bocher M and Juerges N | L33: https://ovidsp.ovid.com/ovidweb.cgi?T=JS&CSC=Y&NEWS=N&PAGE=fulltext&D=med15&AN=29264868 https://discover.lshtm.ac.uk/openurl/44HYG/44HYG_services_page?sid=OVID:medline&id=doi:10.1007%2Fs13280-017-0999-2&id=pmid29264868&issn=0044-7447&isbn=&volume=47&issue=5&spage=608&pages=608-621&date=2018&title=Ambio&atitle=Toward+successful+implementation+of+conservation+research%3A+A+case+study+from+Vietnam.&aulast=Do+Thi&pid=%3Cauthor%3EDo+Thi+H%3BKrott+M%3BBocher+M%3BJuerges+N%3C%2Fauthor%3E%3CAN%3E2926486 | O33: Do Thi, Huong. Chair Group of Forest and Nature Conservation Policy, George-August University of Got | Q33: Do Thi, Huong Krott, Max Bocher, Michael Juerges, Nataly | RAYYAN-INCLUSION: {"Philip"=>"Excluded", "Carlos"=>"Included", "Elina"=>"Included", "fereshteh"=>"Included"} | S33: eppi-reviewer
A34: rayyan-83177464 | B34: What works in conservation? Using expert assessment of summarised evidence to identify practices that enhance natural pest control in agriculture | C34: 2016 | F34: Biodiversity & Conservation | H34: 25 | I34: 7 | J34: 1383-1399 | K34: Dicks Lynn V and Wright Hugh L and Ashpole Joscelyne E and Hutchison James and McCormack Caitlin G and Livoreil Barbara and Zulka Klaus Peter and Sutherland William J | L34: https://ovidsp.ovid.com/ovidweb.cgi?T=JS&CSC=Y&NEWS=N&PAGE=fulltext&D=pmnm3&AN=32355426 https://discover.lshtm.ac.uk/openurl/44HYG/44HYG_services_page?sid=OVID:medline&id=doi:10.1007%2Fs10531-016-1133-7&id=pmid32355426&issn=0960-3115&isbn=&volume=25&issue=7&spage=1383&pages=1383-1399&date=2016&title=Biodiversity+%26+Conservation&atitle=What+works+in+conservation%3F+Using+expert+assessment+of+summarised+evidence+to+identify+practices+that+enhance+natural+pest+control+in+agriculture.&aulast=Dicks& | O34: Dicks, Lynn V. 1Department of Zoology, University of Cambridge, Cambridge, CB2 3QZ UK. Wright, Hugh | Q34: Dicks LV Wright HL Ashpole JE Hutchison J McCormack CG Livoreil B Zulka KP Sutherland WJ | RAYYAN-INCLUSION: {"Matthew"=>"Included", "Philip"=>"Excluded", "fereshteh"=>"Included"} | S34: eppi-reviewer
A35: rayyan-83177466 | B35: Comparing student and professional responses toward advocacy in science | C35: 2016 | F35: Human Dimensions of Wildlife | H35: 21 | I35: 4 | J35: 361-370 | K35: Crawford Brian A and Kramer David W and Hinton Joseph W | L35: https://ovidsp.ovid.com/ovidweb.cgi?T=JS&CSC=Y&NEWS=N&PAGE=fulltext&D=psyc13&AN=2016-26995-007 https://discover.lshtm.ac.uk/openurl/44HYG/44HYG_services_page?sid=OVID:psycdb&id=doi:10.1080%2F10871209.2016.1149747&id=pmid&issn=1087-1209&isbn=&volume=21&issue=4&spage=361&pages=361-370&date=2016&title=Human+Dimensions+of+Wildlife&atitle=Comparing+student+and+professional+responses+toward+advocacy+in+science.&aulast=Crawford&pid=%3Cauthor%3ECrawford%2C+Brian+A%3BKramer%2C+David+W%3BHinton%2C+Joseph | Q35: RAYYAN-INCLUSION: {"Philip"=>"Excluded", "fereshteh"=>"Excluded"} | S35: eppi-reviewer
A36: rayyan-83177468 | B36: Governance Challenges in Joint Inter-Jurisdictional Management: The Grand Teton National Park, Wyoming, Elk Case | C36: 2015 | F36: Environmental Management | H36: 56 | I36: 2 | J36: 286-299 | K36: Clark S G and Vernon M E | L36: https://ovidsp.ovid.com/ovidweb.cgi?T=JS&CSC=Y&NEWS=N&PAGE=fulltext&D=med12&AN=25904468 https://discover.lshtm.ac.uk/openurl/44HYG/44HYG_services_page?sid=OVID:medline&id=doi:10.1007%2Fs00267-015-0515-z&id=pmid25904468&issn=0364-152X&isbn=&volume=56&issue=2&spage=286&pages=286-99&date=2015&title=Environmental+Management&atitle=Governance+Challenges+in+Joint+Inter-Jurisdictional+Management%3A+The+Grand+Teton+National+Park%2C+Wyoming%2C+Elk+Case.&aulast=Clark&pid=%3Cauthor%3EClark+SG%3BVernon+ME%3 | O36: Clark, Susan G. School of Forestry and Environmental Studies, Yale University, 195 Prospect, New Hav | Q36: Clark, Susan G Vernon, Marian E | RAYYAN-INCLUSION: {"Philip"=>"Excluded", "fereshteh"=>"Included", "Sarah"=>"Included"} | S36: eppi-reviewer
A37: rayyan-83177469 | B37: Wyoming sage-grouse working groups: lessons learned | C37: 2017 | F37: Human-Wildlife Interactions | G37: 1934-4392 | H37: 11 | I37: 3 | J37: 274-286 | K37: Christiansen T J and Belton L R | L37: <Go to ISI>://WOS:000422844800012 | Q37: Christiansen, Thomas J. Belton, Lorien R. 1936-8046 | RAYYAN-INCLUSION: {"fereshteh"=>"Excluded"} | S37: eppi-reviewer
A38: rayyan-83177470 | B38: Creating a biodiversity science community: Experiences from a European Network of Knowledge | C38: 2015 | F38: Environmental Science and Policy | H38: 54 | J38: 497-504 | K38: Carmen E and Nesshover C and Saarikoski H and Vandewalle M and Watt A and Wittmer H and Young J | L38: https://ovidsp.ovid.com/ovidweb.cgi?T=JS&CSC=Y&NEWS=N&PAGE=fulltext&D=emed16&AN=603965883 https://discover.lshtm.ac.uk/openurl/44HYG/44HYG_services_page?sid=OVID:embase&id=doi:10.1016%2Fj.envsci.2015.03.014&id=pmid&issn=1462-9011&isbn=&volume=54&issue=&spage=497&pages=497-504&date=2015&title=Environmental+Science+and+Policy&atitle=Creating+a+biodiversity+science+community%3A+Experiences+from+a+European+Network+of+Knowledge&aulast=Carmen&pid=%3Cauthor%3ECarmen+E.%3BNesshover+C.%3BSaarikoski+H.%3 | Q38: RAYYAN-INCLUSION: {"Philip"=>"Included", "fereshteh"=>"Included", "Nibedita"=>"Excluded"} | S38: eppi-reviewer
A39: rayyan-83177471 | B39: A tenuous link: Information transfer between urban ecological research and restoration practice | C39: 2021 | F39: Urban Forestry & Urban Greening | G39: 1618-8667 | H39: 60 | K39: Busbridge S and Clarkson B D and Wallace K J | L39: <Go to ISI>://WOS:000636302300005 | Q39: Busbridge, Sarah Clarkson, Bruce D. Wallace, K. J. 1610-8167 | RAYYAN-INCLUSION: {"Philip"=>"Included", "fereshteh"=>"Excluded", "Iris"=>"Included"} | R39: 10.1016/j.ufug.2021.127019 | S39: eppi-reviewer
A40: rayyan-83177472 | B40: Rural local institutions and climate change adaptation in forest communities in Cameroon | C40: 2015 | F40: Ecology and Society | G40: 1708-3087 | H40: 20 | I40: 2 | K40: Brown H C. P and Sonwa D J | L40: <Go to ISI>://WOS:000357622800007 | Q40: Brown, H. Carolyn Peach Sonwa, Denis J. | RAYYAN-INCLUSION: {"Tabitha"=>"Excluded", "fereshteh"=>"Excluded"} | R40: 10.5751/es-07327-200206 | S40: eppi-reviewer
A41: rayyan-83177473 | B41: Science-based Stakeholder Dialogue for Environmental Policy Implementation | C41: 2021 | F41: Conservation & Society | G41: 0972-4923 | H41: 19 | I41: 4 | J41: 225-235 | K41: Brites A D and de Mello K and Tavares P A and Metzger J P and Rodrigues R R and Molin P G and Pinto L F. G and Joly C A and Fernandes J F. A and Machado F S and Trani E and Sparovek G | L41: <Go to ISI>://WOS:000754309300003 | Q41: Brites, Alice Dantas de Mello, Kaline Tavares, Paulo Andre Metzger, Jean Paul Rodrigues, Ricardo Riberio Molin, Paulo Guilherme Guedes Pinto, Luis Fernando Joly, Carlos Alfredo Adrien Fernandes, Joao Franciso Machado, Frederico Soares Trani, Eduardo Sparovek, Gerd Rodrigues, Ricardo Ribeiro R/D-5557-2012; Molin, Paulo Guilherme/G-9094-2012; Metzger, Jean Paul/C-2514-2012 Rodrigues, Ricardo Ribeiro R/0000-0003-4818-0736; Molin, Paulo Guilherme/0000-0002-4587-935X; Metzger, Jean Paul/0000-0002-0087-5240 0975-3133 | RAYYAN-INCLUSION: {"fereshteh"=>"Excluded"} | R41: 10.4103/cs.cs_20_134 | S41: eppi-reviewer
A42: rayyan-83177475 | B42: Supporting evidence-based policy on biodiversity and ecosystem services: recommendations for effective policy briefs | C42: 2016 | F42: Evidence & Policy | G42: 1744-2648 | H42: 12 | I42: 3 | J42: 431-451 | K42: Balian E V and Drius L and Eggermont H and Livoreil B and Vandewalle M and Vandewoestjine S and Wittmer H and Young J | L42: <Go to ISI>://WOS:000383935900007 | Q42: Balian, Estelle V. Drius, Liza Eggermont, Hilde Livoreil, Barbara Vandewalle, Marie Vandewoestjine, Sofie Wittmer, Heidi Young, Juliette Young, Juliette/B-4225-2012; Wittmer, Heidi/H-7264-2012 Young, Juliette/0000-0002-8522-0883; Wittmer, Heidi/0000-0001-6966-7258; Vandewalle, Marie/0000-0003-3619-9763 1744-2656 Si | RAYYAN-INCLUSION: {"Matthew"=>"Excluded", "Philip"=>"Excluded", "fereshteh"=>"Included"} | R42: 10.1332/174426416x14700777371551 | S42: eppi-reviewer
A43: rayyan-83177476 | B43: Is sharing truly caring? Environmental data value chains and policymaking in Europe and Central Asia | C43: 2020 | F43: Environmental Science and Policy | H43: 114 | J43: 152-161 | K43: Aggestam F and Mangalagiu D | L43: https://ovidsp.ovid.com/ovidweb.cgi?T=JS&CSC=Y&NEWS=N&PAGE=fulltext&D=emed21&AN=2007501625 https://discover.lshtm.ac.uk/openurl/44HYG/44HYG_services_page?sid=OVID:embase&id=doi:10.1016%2Fj.envsci.2020.07.012&id=pmid&issn=1462-9011&isbn=&volume=114&issue=&spage=152&pages=152-161&date=2020&title=Environmental+Science+and+Policy&atitle=Is+sharing+truly+caring%3F+Environmental+data+value+chains+and+policymaking+in+Europe+and+Central+Asia&aulast=Aggestam&pid=%3Cauthor%3EAggestam+F.%3BMangalagiu+D.%3 | Q43: RAYYAN-INCLUSION: {"Philip"=>"Excluded", "Tabitha"=>"Included", "Prishnee"=>"Included", "fereshteh"=>"Excluded"} | S43: eppi-reviewer
A44: rayyan-83177478 | B44: The Use of Spatial Data Infrastructure in Environmental Management:an Example from the Spatial Planning Practice in Poland | C44: 2016 | F44: Environmental Management | H44: 58 | I44: 4 | J44: 619-635 | K44: Zwirowicz-Rutkowska A and Michalik A | L44: https://ovidsp.ovid.com/ovidweb.cgi?T=JS&CSC=Y&NEWS=N&PAGE=fulltext&D=med13&AN=27357806 https://discover.lshtm.ac.uk/openurl/44HYG/44HYG_services_page?sid=OVID:medline&id=doi:10.1007%2Fs00267-016-0732-0&id=pmid27357806&issn=0364-152X&isbn=&volume=58&issue=4&spage=619&pages=619-35&date=2016&title=Environmental+Management&atitle=The+Use+of+Spatial+Data+Infrastructure+in+Environmental+Management%3Aan+Example+from+the+Spatial+Planning+Practice+in+Poland.&aulast=Zwirowicz-Rutkowska&pid=%3Cauthor%3EZw | O44: Zwirowicz-Rutkowska, Agnieszka. Faculty of Geodesy, Geospatial and Civil Engineering, University of | Q44: Zwirowicz-Rutkowska, Agnieszka Michalik, Anna | RAYYAN-INCLUSION: {"Philip"=>"Included", "Prishnee"=>"Included", "Isobel"=>"Included"} | S44: eppi-reviewer
A45: rayyan-83177480 | B45: Knowledge management across the environment-policy interface in China: What knowledge is exchanged, why, and how is this undertaken? | C45: 2019 | F45: Environmental Science and Policy | H45: 92 | J45: 66-75 | K45: Zheng Y and Naylor L A and Waldron S and Oliver D M | L45: https://ovidsp.ovid.com/ovidweb.cgi?T=JS&CSC=Y&NEWS=N&PAGE=fulltext&D=emed20&AN=2001321380 https://discover.lshtm.ac.uk/openurl/44HYG/44HYG_services_page?sid=OVID:embase&id=doi:10.1016%2Fj.envsci.2018.09.021&id=pmid&issn=1462-9011&isbn=&volume=92&issue=&spage=66&pages=66-75&date=2019&title=Environmental+Science+and+Policy&atitle=Knowledge+management+across+the+environment-policy+interface+in+China%3A+What+knowledge+is+exchanged%2C+why%2C+and+how+is+this+undertaken%3F&aulast=Zheng&pid=%3Cauthor% | Q45: RAYYAN-INCLUSION: {"Matthew"=>"Excluded"} | S45: eppi-reviewer
A46: rayyan-83177488 | B46: Assessing the use of climate change information in State Wildlife Action Plans | C46: 2022 | F46: Conservation Science and Practice | H46: 4 | I46: 3 | K46: Yocum H M and Sassorossi D M and Ray A J | L46: <Go to ISI>://WOS:000746626700001 | Q46: Yocum, Heather M. Sassorossi, Deanna Metivier Ray, Andrea J. Ray, Andrea/Q-9848-2018 Ray, Andrea/0000-0001-5385-1202 2578-4854 | RAYYAN-INCLUSION: {"Philip"=>"Included", "fereshteh"=>"Excluded", "Nibedita"=>"Included"} | R46: 10.1111/csp2.608 | S46: eppi-reviewer
A47: rayyan-83177493 | B47: Adaptive governance and the administrative state: knowledge management for forest planning in the western United States | C47: 2019 | F47: Regional Environmental Change | G47: 1436-3798 | H47: 19 | I47: 8 | J47: 2651-2666 | K47: Wurtzebach Z and Schultz C and Waltz A E. M and Esch B E and Wasserman T N | L47: <Go to ISI>://WOS:000511753200039 | Q47: Wurtzebach, Zachary Schultz, Courtney Waltz, Amy E. M. Esch, Bryce E. Wasserman, Tzeidle N. 1436-378x | RAYYAN-INCLUSION: {"Isobel"=>"Included"} | R47: 10.1007/s10113-019-01569-6 | S47: eppi-reviewer
A48: rayyan-83177496 | B48: Science diplomacy in the Arctic: Contributions of the USGS to policy discourse and impact on governance | C48: 2022 | F48: Polar Record | G48: 0032-2474 | H48: 58 | K48: Wood-Donnelly C and Bartels M P | L48: <Go to ISI>://WOS:000809723600001 | Q48: Wood-Donnelly, Corine Bartels, Marianne Pascale 1475-3057 | RAYYAN-INCLUSION: {"Philip"=>"Excluded"} | R48: 10.1017/s0032247422000134 | S48: eppi-reviewer
A49: rayyan-83177498 | B49: Is there enough water? How bearish and bullish outlooks are linked to decision maker perspectives on environmental flows | C49: 2021 | F49: Journal of Environmental Management | H49: 280 | J49: N.PAG-N.PAG | K49: Wineland Sean M and Fovargue Rachel and York Betsey and Lynch Abigail J and Paukert Craig P and Neeson Thomas M | L49: http://0-search.ebscohost.com.catalogue.libraries.london.ac.uk/login.aspx?direct=true&db=a9h&AN=147945436&site=ehost-live | Q49: Wineland, Sean M. 1; Email Address: seanwineland@gmail.com Fovargue, Rachel 1 York, Betsey 2 Lynch, Abigail J. 3 Paukert, Craig P. 4 Neeson, Thomas M. 1; Affiliation: 1: Department of Geography and Environmental Sustainability, University of Oklahoma, Norman, OK, USA 2: Oklahoma Department of Wildlife Conservation, USA 3: U.S. Geological Survey, National Climate Adaptation Science Center, USA 4: U.S. Geological Survey, Missouri Cooperative Fish and Wildlife Research Unit, The School of Natural Resources, University of Missouri, USA; Source Info: Feb2021, Vol. 280, pN.PAG; Subject Term: NETWORK analysis (Communication); Subject Term: WATER supply; Subject Term: NATURAL resources; Subject Term: WATERSHEDS; Subject Term: SOCIAL network analysis; Subject Term: OKLAHOMA; Subject Term: TEXAS; Author-Supplied Keyword: Climate change; Author-Supplied Keyword: Decision making; Author-Supplied Keyword: Environmental flows; Author-Supplied Keyword: Freshwater biodiversity; Author-Supplied Keyword: Policy implementation; Author-Supplied Keyword: Water management; NAICS/Industry Codes: 221310 Water Supply and Irrigation Systems; Number of Pages: 1p; Document Type: Article | RAYYAN-INCLUSION: {"Philip"=>"Excluded", "Tabitha"=>"Included", "fereshteh"=>"Excluded"} | R49: 10.1016/j.jenvman.2020.111694 | S49: eppi-reviewer;NETWORK analy;i;(Communication) WATER;upply NATURAL re;ource;WATERSHEDS SOCIAL network analy;OKLAHOMA TEXAS Climate change Deci;ion making Environmental flow;Fre;hwater biodiver;ity Policy implementation Water management
A50: rayyan-83177504 | B50: (Not So) common places: The roles of ecologists in environmental public policy | C50: 2021 | F50: Environmental Science and Policy | H50: 126 | J50: 223-233 | K50: Weyland F and Von Below J | L50: https://ovidsp.ovid.com/ovidweb.cgi?T=JS&CSC=Y&NEWS=N&PAGE=fulltext&D=emexa&AN=2015183395 https://discover.lshtm.ac.uk/openurl/44HYG/44HYG_services_page?sid=OVID:embase&id=doi:10.1016%2Fj.envsci.2021.10.015&id=pmid&issn=1462-9011&isbn=&volume=126&issue=&spage=223&pages=223-233&date=2021&title=Environmental+Science+and+Policy&atitle=%28Not+So%29+common+places%3A+The+roles+of+ecologists+in+environmental+public+policy&aulast=Weyland&pid=%3Cauthor%3EWeyland+F.%3BVon+Below+J.%3C%2Fauthor%3E%3CAN%3E2 | Q50: RAYYAN-INCLUSION: {"Isobel"=>"Included"} | S50: eppi-reviewer
A51: rayyan-83177509 | B51: Enhancing Great Lakes coastal ecosystems research by initiating engagement between scientists and decision-makers | C51: 2021 | F51: Journal of Great Lakes Research | G51: 0380-1330 | H51: 47 | I51: 4 | J51: 1235-1240 | K51: Weinstein C B and Bourgeau-Chavez L L and Martin S L and Currie W S and Grantham K and Hamlin Q F and Hyndman D W and Kowalski K P and Martina J P and Pearsall D | L51: <Go to ISI>://WOS:000674493000008 | Q51: Weinstein, Charlotte B. Bourgeau-Chavez, Laura L. Martin, Sherry L. Currie, William S. Grantham, Katherine Hamlin, Quercus F. Hyndman, David W. Kowalski, Kurt P. Martina, Jason P. Pearsall, Doug Weinstein, Charlotte/0000-0001-9636-2919; Martina, Jason/0000-0002-3912-4911; Kowalski, Kurt/0000-0002-8424-4701; Martin, Sherry/0000-0001-7471-0476; Hamlin, Quercus/0000-0001-7093-5010 | RAYYAN-INCLUSION: {"Philip"=>"Excluded", "Alec"=>"Included"} | R51: 10.1016/j.jglr.2021.04.018 | S51: eppi-reviewer
A52: rayyan-83177511 | B52: Policy-driven monitoring and evaluation: Does it support adaptive management of socio-ecological systems? | C52: 2019 | F52: Science of the Total Environment | H52: 662 | J52: 373-384 | K52: Waylen Kerry A and Blackstock Kirsty L and van Hulst Freddy J and Damian Carmen and HorvÃ¡th Ferenc and Johnson Richard K and Kanka Robert and KÃ¼lvik Mart and Macleod Christopher J A and Meissner Kristian and Oprina-Pavelescu Mihaela M and Pino Joan and Primmer Eeva and RÃ®È™noveanu Geta and Å atalovÃ¡ Barbora and Silander Jari and Å pulerovÃ¡ Jana and SuÅ¡keviÄs Monika and Van Uytvanck Jan | L52: http://0-search.ebscohost.com.catalogue.libraries.london.ac.uk/login.aspx?direct=true&db=a9h&AN=134797588&site=ehost-live | Q52: Waylen, Kerry A. 1; Email Address: Kerry.Waylen@hutton.ac.uk Blackstock, Kirsty L. 1 van Hulst, Freddy J. 1 Damian, Carmen 1 HorvÃ¡th, Ferenc 1 Johnson, Richard K. 1 Kanka, Robert 1 KÃ¼lvik, Mart 1 Macleod, Christopher J.A. 1 Meissner, Kristian 1 Oprina-Pavelescu, Mihaela M. 1 Pino, Joan 1 Primmer, Eeva 1 RÃ®È™noveanu, Geta 1 Å atalovÃ¡, Barbora 1 Silander, Jari 1 Å pulerovÃ¡, Jana 1 SuÅ¡keviÄs, Monika 1 Van Uytvanck, Jan 1; Affiliation: 1: Social, Economic &amp; Geographical Sciences, The James Hutton Institute, Cragiebuckler, Scotland AB15 8QH, UK; Source Info: Apr2019, Vol. 662, p373; Author-Supplied Keyword: Adaptive management; Author-Supplied Keyword: Environmental governance; Author-Supplied Keyword: Monitoring &amp; evaluation; Author-Supplied Keyword: Policy; Author-Supplied Keyword: Socio-ecological systems; Author-Supplied Keyword: Sustainability; Number of Pages: 12p; Document Type: Article; Full Text Word Count: 12690 | RAYYAN-INCLUSION: {"Philip"=>"Excluded", "Aidan"=>"Excluded"} | R52: 10.1016/j.scitotenv.2018.12.462 | S52: eppi-reviewer;Adaptive management Environmental governance Monitoring & evaluation Policy Socio-ecological;y;tem;Su;tainability
A53: rayyan-83177526 | B53: Not Learning from the Past: Adaptive Governance Challenges for Australian Natural Resource Management | C53: 2015 | F53: Geographical Research | H53: 53 | I53: 4 | J53: 379-392 | K53: Vella Karen and Sipe Neil and Dale Allan and Taylor Bruce | L53: http://0-search.ebscohost.com.catalogue.libraries.london.ac.uk/login.aspx?direct=true&db=a9h&AN=110482322&site=ehost-live | Q53: VELLA, KAREN 1 SIPE, NEIL 2 DALE, ALLAN 3 TAYLOR, BRUCE 4; Affiliation: 1: Queensland University of Technology 2: University of Queensland 3: James Cook University 4: CSIRO; Source Info: Nov2015, Vol. 53 Issue 4, p379; Subject Term: NATURAL resources management; Subject Term: GRASSROOTS movements; Subject Term: SOCIAL movements; Subject Term: COMMUNITY support; Subject Term: DECISION making; Subject Term: AUSTRALIA; Author-Supplied Keyword: adaptive governance; Author-Supplied Keyword: Australia; Author-Supplied Keyword: evaluation; Author-Supplied Keyword: natural resource management; Author-Supplied Keyword: planning; NAICS/Industry Codes: 924110 Administration of Air and Water Resource and Solid Waste Management Programs; Number of Pages: 15p; Illustrations: 5 Charts; Document Type: Article | RAYYAN-INCLUSION: {"Tabitha"=>"Excluded"} | R53: 10.1111/1745-5871.12115 | S53: eppi-reviewer;NATURAL re;ource;management GRASSROOTS movement;SOCIAL movement;COMMUNITY;upport DECISION making AUSTRALIA adaptive governance evaluation natural re;ource management planning
A54: rayyan-83177529 | B54: Enhancing interoperability to facilitate implementation of REDD+: case study of Mexico | C54: 2017 | F54: Carbon Management | H54: 8 | I54: 1 | J54: 57-65 | K54: Vargas Rodrigo and Alcaraz-Segura Domingo and Birdsey Richard and Brunsell Nathaniel A and Cruz-Gaistardo Carlos O and de Jong Bernardus and Etchevers Jorge and Guevara Mario and Hayes Daniel J and Johnson Kristofer and Loescher Henry W and Paz Fernando and Ryu Youngryel and Sanchez-Mejia Zulia and Toledo-Gutierrez Karla P | L54: http://0-search.ebscohost.com.catalogue.libraries.london.ac.uk/login.aspx?direct=true&db=a9h&AN=122857161&site=ehost-live | Q54: Vargas, Rodrigo 1; Email Address: rvargas@udel.edu Alcaraz-Segura, Domingo 2,3 Birdsey, Richard 4 Brunsell, Nathaniel A. 5 Cruz-Gaistardo, Carlos O. 6 de Jong, Bernardus 7 Etchevers, Jorge 8 Guevara, Mario 1 Hayes, Daniel J. 9 Johnson, Kristofer 4 Loescher, Henry W. 10 Paz, Fernando 8 Ryu, Youngryel 11 Sanchez-Mejia, Zulia 1 Toledo-Gutierrez, Karla P. 1; Affiliation: 1: Department of Plant &amp; Soil Sciences, University of Delaware, Newark, DE, USA 19716 2: Departamento de BotÃ¡nica, and Instituto Interuniversitario para la InvestigaciÃ³n del Sistema Tierra en AndalucÃ­a (IISTA), Universidad de Granada, Granada, Spain, 18006 3: Andalusian Center for the Assessment and Monitoring of Global Change (CAESCG), Universidad de AlmerÃ­a, AlmerÃ­a, Spain, 04120 4: Northern Research Station, USDA Forest Service, Newtown Square, PA, USA 19073 5: Department of Geography and Atmospheric Science, University of Kansas, Lawrence, KS, USA 66044 6: Departamento de Suelos, Instituto Nacional de EstadÃ­stica y GeografÃ­a, Aguascalientes, Mexico, 20196 7: El Colegio de la Frontera Sur 8: Colegio de Postgraduados, Montecillo, Mexico, 56230 9: School of Forest Resources, University of Maine, Orono, ME, USA, 04469 10: Battelleâ€“National Ecological Observatory Network (NEON), Boulder, CO USA 80301, and the Institute of Alpine and Arctic Research (INSTAAR), University of Colorado, Boulder, CO USA 80301 11: Department of Landscape Architecture and Rural Systems Engineering, Seoul National University, Seoul, South Korea, 151-921; Source Info: Feb2017, Vol. 8 Issue 1, p57; Subject Term: DEFORESTATION; Subject Term: ENVIRONMENTAL policy; Subject Term: FOREST degradation; Author-Supplied Keyword: adaptive governance; Author-Supplied Keyword: developing countries; Author-Supplied Keyword: good practices; Author-Supplied Keyword: measurement, reporting and verification (MRV); NAICS/Industry Codes: 912910 Other provincial and territorial public administration; NAICS/Industry Codes: 924110 Administration of Air and Water Resource and Solid Waste Management Programs; Number of Pages: 9p; Document Type: Article | RAYYAN-INCLUSION: {"Alec"=>"Excluded"} | R54: 10.1080/17583004.2017.1285177 | S54: eppi-reviewer;DEFORESTATION ENVIRONMENTAL policy FOREST degradation adaptive governance developing countrie;good practice;mea;urement;reporting and verification (MRV)
A55: rayyan-83177533 | B55: Understanding socio-cultural dimensions of environmental decision-making: A knowledge governance approach | C55: 2017 | F55: Environmental Science and Policy | H55: 73 | J55: 29-37 | K55: van Kerkhoff L and Pilbeam V | L55: https://ovidsp.ovid.com/ovidweb.cgi?T=JS&CSC=Y&NEWS=N&PAGE=fulltext&D=emed18&AN=615225352 https://discover.lshtm.ac.uk/openurl/44HYG/44HYG_services_page?sid=OVID:embase&id=doi:10.1016%2Fj.envsci.2017.03.011&id=pmid&issn=1462-9011&isbn=&volume=73&issue=&spage=29&pages=29-37&date=2017&title=Environmental+Science+and+Policy&atitle=Understanding+socio-cultural+dimensions+of+environmental+decision-making%3A+A+knowledge+governance+approach&aulast=van+Kerkhoff&pid=%3Cauthor%3Evan+Kerkhoff+L.%3BPilbeam | Q55: RAYYAN-INCLUSION: {"Isobel"=>"Included"} | S55: eppi-reviewer
A56: rayyan-83177534 | B56: Working at the Boundary: An Empirical Study into the Goals and Strategies of Knowledge Brokers in the Field of Environmental Governance in the Netherlands | C56: 2017 | F56: Sustainability | H56: 9 | I56: 11 | K56: van Enst W I and Driessen P P. J and Runhaar H A. C | L56: <Go to ISI>://WOS:000416793400042 | Q56: van Enst, Wynanda I. Driessen, Peter P. J. Runhaar, Hens A. C. Runhaar, Hens A.C./L-5395-2013; Driessen, Peter/M-6751-2013 Runhaar, Hens A.C./0000-0001-7790-097X; Driessen, Peter/0000-0002-0724-6666 2071-1050 | RAYYAN-INCLUSION: {"Nibedita"=>"Excluded"} | R56: 10.3390/su9111962 | S56: eppi-reviewer
A57: rayyan-83177537 | B57: Benefits and Limitations of Using Decision-Analytic Tools to Assess Uncertainty and Prioritize Landscape Conservation Cooperative Information Needs | C57: 2016 | F57: Journal of Fish and Wildlife Management | G57: 1944-687X | H57: 7 | I57: 1 | J57: 280-290 | K57: van der Burg M P and Thomas C C and Holcombe T and Nelson R D | L57: <Go to ISI>://WOS:000378082600027 | Q57: van der Burg, Max Post Thomas, Catherine Cullinane Holcombe, Tracy Nelson, Richard D. Post van der Burg, Max/0000-0002-3943-4194 | RAYYAN-INCLUSION: {"Isobel"=>"Excluded"} | R57: 10.3996/032015-jfwm-023 | S57: eppi-reviewer
A58: rayyan-83177540 | B58: Rhizomic learning: How environmental non-governmental organizations (ENGOs) acquire and assemble knowledge | C58: 2020 | F58: Social Studies of Science | H58: 50 | I58: 5 | J58: 821-833 | K58: Unander T E and Sorensen K H | L58: https://ovidsp.ovid.com/ovidweb.cgi?T=JS&CSC=Y&NEWS=N&PAGE=fulltext&D=med20&AN=32077374 https://discover.lshtm.ac.uk/openurl/44HYG/44HYG_services_page?sid=OVID:medline&id=doi:10.1177%2F0306312720908343&id=pmid32077374&issn=0306-3127&isbn=&volume=50&issue=5&spage=821&pages=821-833&date=2020&title=Social+Studies+of+Science&atitle=Rhizomic+learning%3A+How+environmental+non-governmental+organizations+%28ENGOs%29+acquire+and+assemble+knowledge.&aulast=Unander&pid=%3Cauthor%3EUnander+TE%3BSorensen+KH% | O58: Unander, Trine E. Department of Interdisciplinary Studies of Culture, Norwegian University of Scienc | Q58: Unander, Trine E Sorensen, Knut H | RAYYAN-INCLUSION: {"Alice"=>"Excluded", "fereshteh"=>"Excluded"} | S58: eppi-reviewer
A59: rayyan-83177550 | B59: From knowledge to action: Bridging the gaps toward effective incorporation of Landscape Character Assessment approach in land-use planning and management in Israel | C59: 2017 | F59: Land Use Policy | G59: 0264-8377 | H59: 61 | J59: 220-230 | K59: Trop T | L59: <Go to ISI>://WOS:000392766800020 | Q59: Trop, Tamar Trop, Tamar/0000-0002-5865-5195 1873-5754 | RAYYAN-INCLUSION: {"Tabitha"=>"Included"} | R59: 10.1016/j.landusepol.2016.10.052 | S59: eppi-reviewer
A60: rayyan-83177554 | B60: An optimistic outlook on the use of evidence syntheses to inform environmental decision-making | C60: 2021 | F60: Conservation Science and Practice | H60: 3 | I60: 6 | K60: Thomas-Walters L and Nyboer E A and Taylor J J and Rytwinski T and Lane J F and Young N and Bennett J R and Nguyen V M and Harron N and Aitken S M and Auld G and Browne D and Jacob A L and Prior K and Smith P A and Smokorowski K E and Alexander S M and Cooke S J | L60: <Go to ISI>://WOS:000636760900001 | Q60: Thomas-Walters, Laura Nyboer, Elizabeth A. Taylor, Jessica J. Rytwinski, Trina Lane, John F. Young, Nathan Bennett, Joseph R. Nguyen, Vivian M. Harron, Nathan Aitken, Susan M. Auld, Graeme Browne, David Jacob, Aerin L. Prior, Kent Smith, Paul A. Smokorowski, Karen E. Alexander, Steven M. Cooke, Steven J. Auld, Graeme/ABD-8264-2021; Cooke, Steven J/F-4193-2010 Cooke, Steven J/0000-0002-5407-0659; Auld, Graeme/0000-0002-4054-7284; Thomas-Walters, Laura/0000-0002-3250-2799; Browne, David/0000-0002-1821-0191 2578-4854 | RAYYAN-INCLUSION: {"Tabitha"=>"Included"} | R60: 10.1111/csp2.426 | S60: eppi-reviewer
A61: rayyan-83177562 | B61: Building sustainability in the Eastern Himalaya: linking evidence to action | C61: 2020 | F61: Environment Development and Sustainability | G61: 1387-585X | H61: 22 | I61: 6 | J61: 5887-5903 | K61: Tambe S and Rawat G S and Bhutia N T and Sherpa P N and Dhakal S and Pradhan S and Kulkarni H and Arrawatia M L | L61: <Go to ISI>://WOS:000545217400046 | Q61: Tambe, Sandeep Rawat, Gopal S. Bhutia, Nima Tashi Sherpa, Pem Norbu Dhakal, Subash Pradhan, Sarika Kulkarni, Himanshu Arrawatia, M. L. 1573-2975 | RAYYAN-INCLUSION: {"Prishnee"=>"Included", "fereshteh"=>"Included", "Nibedita"=>"Excluded"} | R61: 10.1007/s10668-019-00456-8 | S61: eppi-reviewer
A62: rayyan-83177565 | B62: Crossing Science-Policy-Societal Boundaries to Reduce Scientific and Institutional Uncertainty in Small-Scale Fisheries | C62: 2016 | F62: Environmental Management | G62: 0364-152X | H62: 58 | I62: 4 | J62: 565-584 | K62: Sutton A M and Rudd M A | L62: <Go to ISI>://WOS:000384420900001 | Q62: Sutton, Abigail M. Rudd, Murray A. Rudd, Murray/C-1244-2009 Rudd, Murray/0000-0001-9533-5070 1432-1009 | RAYYAN-INCLUSION: {"Matthew"=>"Included"} | R62: 10.1007/s00267-016-0737-8 | S62: eppi-reviewer
A63: rayyan-83177571 | B63: Channelling science into policy: enabling best practices from research on land degradation and sustainable land management in dryland Africa | C63: 2013 | F63: Journal of Environmental Management | H63: 114 | J63: 328-335 | K63: Stringer L C and Dougill A J | L63: https://ovidsp.ovid.com/ovidweb.cgi?T=JS&CSC=Y&NEWS=N&PAGE=fulltext&D=med10&AN=23158525 https://discover.lshtm.ac.uk/openurl/44HYG/44HYG_services_page?sid=OVID:medline&id=doi:10.1016%2Fj.jenvman.2012.10.025&id=pmid23158525&issn=0301-4797&isbn=&volume=114&issue=&spage=328&pages=328-35&date=2013&title=Journal+of+Environmental+Management&atitle=Channelling+science+into+policy%3A+enabling+best+practices+from+research+on+land+degradation+and+sustainable+land+management+in+dryland+Africa.&aulast=Strin | O63: Stringer, Lindsay C. Sustainability Research Institute, School of Earth and Environment, University | Q63: Stringer, Lindsay C Dougill, Andrew J | RAYYAN-INCLUSION: {"Iris"=>"Excluded"} | S63: eppi-reviewer
A64: rayyan-83177575 | B64: The systems approach framework for collaborative, science-based management of complex systems | C64: 2019 | F64: Journal of Coastal Conservation (Springer Science & Business Media B.V.) | H64: 23 | I64: 5 | J64: 881-898 | K64: StÃ¸ttrup Josianne G and Dinesen Grete E and Schumacher Johanna and Gillgren Christina and InÃ¡cio Miguel and Schernewski Gerald | L64: http://0-search.ebscohost.com.catalogue.libraries.london.ac.uk/login.aspx?direct=true&db=a9h&AN=139438687&site=ehost-live | Q64: StÃ¸ttrup, Josianne G. 1; Email Address: jgs@aqua.dtu.dk Dinesen, Grete E. 1 Schumacher, Johanna 2 Gillgren, Christina 3 InÃ¡cio, Miguel 2,4 Schernewski, Gerald 2,4; Affiliation: 1: DTU Aqua, National Institute of Aquatic Resources, Technical University of Denmark, Kemitorvet, DK-2800, Kongens Lyngby, Denmark 2: Leibniz-Institute for Baltic Sea Research WarnemÃ¼nde, Seestrasse 15, D-18119, Rostock, Germany 3: Gillgren and Associates, 15 Kent Street, 6157, Bicton, WA, Australia 4: Marine Science Institute, Klaipeda University, Herkus Mantas str. 84, LT-92294, Klaipeda, Lithuania; Source Info: Oct2019, Vol. 23 Issue 5, p881; Subject Term: STAKEHOLDER theory; Subject Term: INTEGRATED coastal zone management; Subject Term: COASTAL zone management; Subject Term: PROGRESS; Subject Term: SUSTAINABLE development; Author-Supplied Keyword: Integrated coastal management; Author-Supplied Keyword: Science-policy; Author-Supplied Keyword: Stakeholder engagement; Author-Supplied Keyword: System analyses; NAICS/Industry Codes: 926110 Administration of General Economic Programs; Number of Pages: 18p; Document Type: Article | RAYYAN-INCLUSION: {"Iris"=>"Excluded"} | R64: 10.1007/s11852-018-00677-5 | S64: eppi-reviewer;STAKEHOLDER theory INTEGRATED coa;tal zone management COASTAL zone management PROGRESS SUSTAINABLE development Integrated coa;tal management Science-policy Stakeholder engagement Sy;tem analy;e
A65: rayyan-83177576 | B65: Roleâ€playing games in natural resource management and research: Lessons learned from theory and practice | C65: 2018 | H65: 184 | J65: 298-309 | K65: Stollâ€Kleemann Susanne | L65: http://0-search.ebscohost.com.catalogue.libraries.london.ac.uk/login.aspx?direct=true&db=a9h&AN=131116107&site=ehost-live | N65: Wiley-Blackwell | Q65: Accession Number: 131116107; Wesselow, Maren 1; Email Address: maren.wesselow@uni-oldenburg.de Stollâ€Kleemann, Susanne 2; Affiliation: 1: Carl von Ossietzky UniversitÃ¤t Oldenburg, Oldenburg, Germany 2: Ernstâ€Moritzâ€Arndtâ€UniversitÃ¤t Greifswald, Greifswald, Germany; Source Info: Sep2018, Vol. 184 Issue 3, p298; Subject Term: ROLEPLAYING games; Subject Term: NATURAL resources management; Subject Term: RESEARCH methodology; Subject Term: ENVIRONMENTAL research; Author-Supplied Keyword: game design; Author-Supplied Keyword: Madagascar; Author-Supplied Keyword: natural resource management; Author-Supplied Keyword: participatory methods; Author-Supplied Keyword: roleâ€playing games; Author-Supplied Keyword: stakeholders; NAICS/Industry Codes: 924110 Administration of Air and Water Resource and Solid Waste Management Programs; Number of Pages: 12p; Illustrations: 1 Chart; Document Type: Case Study; Full Text Word Count: 8278 | RAYYAN-INCLUSION: {"fereshteh"=>"Excluded", "Nibedita"=>"Excluded"} | R65: 10.1111/geoj.12248 | S65: eppi-reviewer;ROLEPLAYING game;NATURAL re;ource;management RESEARCH methodology ENVIRONMENTAL re;earch game de;ign Madaga;car natural re;ource management participatory method;roleâ€playing game;takeholder
A66: rayyan-83177579 | B66: Improving the scienceâ€“policyâ€“practice interface: decision support system uptake and use in the forestry sector in Great Britain | C66: 2014 | F66: Scandinavian Journal of Forest Research | H66: 29 | J66: 144-153 | K66: Stewart Amy and Edwards David and Lawrence Anna | L66: http://0-search.ebscohost.com.catalogue.libraries.london.ac.uk/login.aspx?direct=true&db=a9h&AN=99712807&site=ehost-live | Q66: Stewart, Amy 1; Email Address: amy.stewart@forestry.gsi.gov.uk Edwards, David 1 Lawrence, Anna 1; Affiliation: 1: Forest Research, Northern Research Station, Bush Estate, RoslinEH25 9SY, Scotland; Source Info: Dec2014 Supplement, Vol. 29, p144; Subject Term: DECISION support systems; Subject Term: FORESTS &amp; forestry; Subject Term: FOREST management; Subject Term: FOREST surveys; Subject Term: INFORMATION sharing; Subject Term: UNITED Kingdom; Author-Supplied Keyword: adoption; Author-Supplied Keyword: decision support systems; Author-Supplied Keyword: forestry; Author-Supplied Keyword: implementation; Author-Supplied Keyword: knowledge exchange; Author-Supplied Keyword: model; Author-Supplied Keyword: uptake; Company/Entity: INSTITUTE of Chartered Foresters (Great Britain) Company/Entity: GREAT Britain. Forestry Commission; NAICS/Industry Codes: 115310 Support Activities for Forestry; Number of Pages: 10p; Document Type: Article | RAYYAN-INCLUSION: {"Isobel"=>"Included"} | R66: 10.1080/02827581.2013.849358 | S66: eppi-reviewer;DECISION;upport;y;tem;FORESTS & fore;try FOREST management FOREST;urvey;INFORMATION;haring UNITED Kingdom adoption fore;try implementation knowledge exchange model uptake INSTITUTE of Chartered Fore;ter;(Great Britain) GREAT Britain. Fore;try Commi;ion
A67: rayyan-83177582 | B67: From ecological knowledge to conservation policy: a case study on green tree retention and continuous-cover forestry in Sweden | C67: 2019 | F67: Biodiversity and Conservation | G67: 0960-3115 | H67: 28 | I67: 13 | J67: 3547-3574 | K67: Stens A and Roberge J M and Lofmarck E and Lindahl K B and Felton A and Widmark C and Rist L and Johansson J and Nordin A and Nilsson U and Laudon H and Ranius T | L67: <Go to ISI>://WOS:000488929900009 | Q67: Stens, Anna Roberge, Jean-Michel Lofmarck, Erik Lindahl, Karin Beland Felton, Adam Widmark, Camilla Rist, Lucy Johansson, Johanna Nordin, Annika Nilsson, Urban Laudon, Hjalmar Ranius, Thomas Stens, Anna/0000-0002-2739-0497; Widmark, Camila/0000-0002-1559-6471; Johansson, Johanna/0000-0001-6823-3503 1572-9710 | RAYYAN-INCLUSION: {"Matthew"=>"Included"} | R67: 10.1007/s10531-019-01836-2 | S67: eppi-reviewer
A68: rayyan-83177591 | B68: Towards better integration of environmental science in society: Lessons from BONUS, the joint Baltic Sea environmental research and development programme | C68: 2017 | F68: Environmental Science and Policy | H68: 78 | J68: 193-209 | K68: Snoeijs-Leijonmalm P and Barnard S and Elliott M and Andrusaitis A and Kononen K and Sirola M | L68: https://ovidsp.ovid.com/ovidweb.cgi?T=JS&CSC=Y&NEWS=N&PAGE=fulltext&D=emed18&AN=620912897 https://discover.lshtm.ac.uk/openurl/44HYG/44HYG_services_page?sid=OVID:embase&id=doi:10.1016%2Fj.envsci.2017.10.004&id=pmid&issn=1462-9011&isbn=&volume=78&issue=&spage=193&pages=193-209&date=2017&title=Environmental+Science+and+Policy&atitle=Towards+better+integration+of+environmental+science+in+society%3A+Lessons+from+BONUS%2C+the+joint+Baltic+Sea+environmental+research+and+development+programme&aulast=S | Q68: RAYYAN-INCLUSION: {"Matthew"=>"Excluded"} | S68: eppi-reviewer
A69: rayyan-83177597 | B69: Community-Based Environmental Monitoring (CBEM) for Meaningful Incorporation of Indigenous and Local Knowledge Within the Context of the Canadian Northern Corridor Program | C69: 2022 | F69: The School of Public Policy Publications (SPPP) | G69: 25608320 | H69: 15 | K69: Sidorova Jen and Virla Luis D | L69: https://www.proquest.com/scholarly-journals/community-based-environmental-monitoring-cbem/docview/2673033210/se-2 https://ucl-new-primo.hosted.exlibrisgroup.com/openurl/UCL/UCL_VU2?url_ver=Z39.88-2004&rft_val_fmt=info:ofi/fmt:kev:mtx:journal&genre=article&sid=ProQ:ProQ%3Aibss&atitle=Community-Based+Environmental+Monitoring+%28CBEM%29+for+Meaningful+Incorporation+of+Indigenous+and+Local+Knowledge+Within+the+Context+of+the+Canadian+Northern+Corridor+Program&title=The+School+of+Public+Policy+Publi | Q69: Copyright - Â© 2022. This work is licensed under https://creativecommons.org/licenses/by-nc/4.0/ (the â€œLicenseâ€). Notwithstanding the ProQuest Terms and Conditions, you may use this content in accordance with the terms of the License. | RAYYAN-INCLUSION: {"Alec"=>"Excluded"} | R69: https://doi.org/10.11575/sppp.v15i1.73981 | S69: eppi-reviewer;Social Sciences: Comprehensive Works;Environmental issues;Incorporation;Sustainable development;Emotional development;Community;Policy analysis;Development projects;Volunteers;Program implementation;Water quality;Policy making;Community based;Local knowledge;Mitigation;Leadership;Infrastructure;Conflict resolution;Pollution;Water pollution;Sustainability;Development policy;Economic development;Indigenous peoples;Case studies;Implementation;Climate change;Environmental monitoring;Technology;Caribou;Native peoples;Berries
A70: rayyan-83177615 | B70: The use of knowledge in evidence-informed voluntary conservation of Finnish forests | C70: 2016 | F70: Forest Policy and Economics | G70: 1389-9341 | H70: 73 | J70: 90-98 | K70: Salomaa A and Paloniemi R and Hujala T and Rantala S and Arponen A and Niemela J | L70: <Go to ISI>://WOS:000388059900010 | Q70: Salomaa, Anna Paloniemi, Riikka Hujala, Teppo Rantala, Salla Arponen, Anni Niemela, Jari Arponen, Anni/AAB-8851-2022 Arponen, Anni/0000-0002-6721-7795; Salomaa, Anna/0000-0002-0509-4873; Hujala, Teppo/0000-0002-7905-7602; Paloniemi, Riikka/0000-0003-2853-535X; Rantala, Salla/0000-0002-8135-4569 1872-7050 | RAYYAN-INCLUSION: {"Alec"=>"Included"} | R70: 10.1016/j.forpol.2016.09.004 | S70: eppi-reviewer
A71: rayyan-83177620 | B71: Pathways to policy impact: a new approach for planning and evidencing research impact | C71: 2018 | F71: Evidence and Policy | H71: 14 | I71: 3 | J71: 431-458 | K71: S Reed Mark and Rosalind Bryce and Ruth Machen | L71: http://www.scie-socialcareonline.org.uk/pathways-to-policy-impact-a-new-approach-for-planning-and-evidencing-research-impact/r/a1C0f000006iJxaEAE https://ovidsp.ovid.com/ovidweb.cgi?T=JS&CSC=Y&NEWS=N&PAGE=fulltext&D=sopp&AN=SCIEa1C0f000006iJxaEAE https://discover.lshtm.ac.uk/openurl/44HYG/44HYG_services_page?sid=OVID:soppdb&id=doi:&id=pmid&issn=1744-2656&isbn=&volume=14&issue=3&spage=431&pages=431-458&date=2018&title=Evidence+and+Policy&atitle=Pathways+to+policy+impact%3A+a+new+approach+for+pl | Q71: Using Smart Source Parsing pp. 2018 | RAYYAN-INCLUSION: {"Elina"=>"Excluded"} | S71: eppi-reviewer;outcomes;research;research dissemination;research implementation;social networks;evaluation;evidence based practice;models
A72: rayyan-83177623 | B72: A pathway for citizen science data to inform policy: A case study using data for defining low-risk collision areas for wind energy development | C72: 2021 | F72: Journal of Applied Ecology | G72: 0021-8901 | H72: 58 | I72: 6 | J72: 1104-1111 | K72: Ruiz-Gutierrez V and Bjerre E R and Otto M C and Zimmerman G S and Millsap B A and Fink D and Stuber E F and Strimas-Mackey M and Robinson O J | L72: <Go to ISI>://WOS:000639639700001 | Q72: Ruiz-Gutierrez, Viviana Bjerre, Emily R. Otto, Mark C. Zimmerman, Guthrie S. Millsap, Brian A. Fink, Daniel Stuber, Erica F. Strimas-Mackey, Matthew Robinson, Orin J. Stuber, Erica/0000-0002-2687-6874; Millsap, Brian/0000-0003-3969-249X; Strimas-Mackey, Matthew/0000-0001-8929-7776; Robinson, Orin/0000-0001-8935-1242; Ruiz-Gutierrez, Viviana/0000-0001-7116-1168; Otto, Mark/0000-0002-0552-7771 1365-2664 | RAYYAN-INCLUSION: {"Alec"=>"Excluded"} | R72: 10.1111/1365-2664.13870 | S72: eppi-reviewer
A73: rayyan-83177627 | B73: Process matters: a framework for conducting decision-relevant assessments of ecosystem services | C73: 2015 | F73: International Journal of Biodiversity Science, Ecosystem Services & Management | H73: 11 | I73: 3 | J73: 190-204 | K73: Rosenthal Amy and Verutes Gregory and McKenzie Emily and Arkema Katie K and Bhagabati Nirmal and Bremer Leah L and Olwero Nasser and Vogl Adrian L | L73: http://0-search.ebscohost.com.catalogue.libraries.london.ac.uk/login.aspx?direct=true&db=a9h&AN=108866541&site=ehost-live | Q73: Rosenthal, Amy 1; Email Address: amy.rosenthal@wwfus.org Verutes, Gregory 1,2 McKenzie, Emily 1,3 Arkema, Katie K. 2 Bhagabati, Nirmal 1 Bremer, Leah L. 2 Olwero, Nasser 1 Vogl, Adrian L. 2; Affiliation: 1: The Natural Capital Project, World Wildlife Fund (WWF-US), Washington, DC, USA 2: The Natural Capital Project, Woods Institute for the Environment, Stanford University, Stanford, CA, USA 3: World Wide Fund for Nature (WWF-UK), Surrey, England; Source Info: Sep2015, Vol. 11 Issue 3, p190; Subject Term: ECOSYSTEM services; Subject Term: DECISION support systems; Subject Term: GUIDELINES; Subject Term: QUALITY of service; Subject Term: STAKEHOLDER analysis; Author-Supplied Keyword: capacity-building; Author-Supplied Keyword: decision support; Author-Supplied Keyword: ecosystem services; Author-Supplied Keyword: enabling conditions; Author-Supplied Keyword: iteration; Author-Supplied Keyword: monitoring; Author-Supplied Keyword: scenarios; Author-Supplied Keyword: science-policy; Number of Pages: 15p; Document Type: Article | RAYYAN-INCLUSION: {"Isobel"=>"Excluded"} | R73: 10.1080/21513732.2014.966149 | S73: eppi-reviewer;ECOSYSTEM;ervice;DECISION;upport;y;tem;GUIDELINES QUALITY of;ervice STAKEHOLDER analy;i;capacity-building deci;ion;upport enabling condition;iteration monitoring;cenario;cience-policy
A74: rayyan-83177646 | B74: Achieving impact from ecosystem assessment and valuation of urban greenspace: The case of i-Tree Eco in Great Britain | C74: 2019 | F74: Landscape and Urban Planning | G74: 0169-2046 | H74: 190 | K74: Raum S and Hand K L and Hall C and Edwards D M and O'Brien L and Doick K J | L74: <Go to ISI>://WOS:000484871000011 | Q74: Raum, S. Hand, K. L. Hall, C. Edwards, D. M. O'Brien, L. Doick, K. J. Raum, Susanne/AAW-5732-2020; O'Brien, Liz/AEO-7315-2022 Raum, Susanne/0000-0003-3795-3836; O'Brien, Liz/0000-0001-7976-9987; Hand, Kathryn/0000-0003-4598-2469 1872-6062 | RAYYAN-INCLUSION: {"Sarah"=>"Included"} | R74: 10.1016/j.landurbplan.2019.103590 | S74: eppi-reviewer
A75: rayyan-83177648 | B75: Adaptation by stealth: climate information use in the Great Lakes region across scales | C75: 2017 | F75: Climatic Change | H75: 140 | I75: 3 | J75: 451-465 | K75: Rasmussen Laura and Kirchhoff Christine and Lemos Maria | L75: http://0-search.ebscohost.com.catalogue.libraries.london.ac.uk/login.aspx?direct=true&db=a9h&AN=120947581&site=ehost-live | Q75: Rasmussen, Laura 1; Email Address: laura_vang@yahoo.dk Kirchhoff, Christine 2 Lemos, Maria 1; Affiliation: 1: School of Natural Resources and Environment , University of Michigan , Ann Arbor USA 2: University of Connecticut , Storrs USA; Source Info: Feb2017, Vol. 140 Issue 3/4, p451; Subject Term: BIOLOGICAL adaptation; Subject Term: PUBLIC opinion on climate change; Subject Term: DECISION making in environmental policy; Subject Term: EFFECT of human beings on climate change; Subject Term: GREAT Lakes Region (North America); Number of Pages: 15p; Document Type: Article | RAYYAN-INCLUSION: {"Sarah"=>"Included"} | R75: 10.1007/s10584-016-1857-0 | S75: eppi-reviewer;BIOLOGICAL adaptation PUBLIC opinion on climate change DECISION making in environmental policy EF...;on climate change GREAT Lake;Region (North America)
A76: rayyan-83177649 | B76: Governance of forests and governance of forest information: Interlinkages in the age of open and digital data | C76: 2020 | F76: Forest Policy and Economics | G76: 1389-9341 | H76: 113 | K76: Rantala S and Swallow B and Paloniemi R and Raitanen E | L76: <Go to ISI>://WOS:000519530000004 | Q76: Rantala, Salla Swallow, Brent Paloniemi, Riikka Raitanen, Elina Rantala, Salla/0000-0002-8135-4569 1872-7050 | RAYYAN-INCLUSION: {"Philip"=>"Excluded", "Carlos"=>"Excluded", "Prishnee"=>"Included"} | R76: 10.1016/j.forpol.2020.102123 | S76: eppi-reviewer
A77: rayyan-83177650 | B77: Understanding barriers and opportunities for diffusion of an agricultural decision-support tool: An organizational perspective | C77: 2022 | F77: Journal of Hydrology | H77: 607 | J77: N.PAG-N.PAG | K77: Ranjan Pranay and Usher Emily M and Bates Hanna T and Zimmerman Emily K and Tyndall John C and Morris Chris J and Koontz Tomas M and Prokopy Linda S | L77: http://0-search.ebscohost.com.catalogue.libraries.london.ac.uk/login.aspx?direct=true&db=a9h&AN=155692757&site=ehost-live | Q77: Ranjan, Pranay 1; Email Address: ranjanp@purdue.edu Usher, Emily M. 1 Bates, Hanna T. 2 Zimmerman, Emily K. 3 Tyndall, John C. 3 Morris, Chris J. 4 Koontz, Tomas M. 5 Prokopy, Linda S. 6; Affiliation: 1: Department of Forestry &amp; Natural Resources, Purdue University, United States 2: Iowa Water Center, Iowa State University, United States 3: Natural Resource Ecology and Management, Iowa State University, United States 4: Department of Sociology and Criminal Justice, Iowa State University, United States 5: School of Interdisciplinary Arts &amp; Sciences, University of Washington Tacoma, United States 6: Department of Horticulture and Landscape Architecture, Purdue University, United States; Source Info: Apr2022, Vol. 607, pN.PAG; Subject Term: AGRICULTURAL implements; Subject Term: NONPOINT source pollution; Subject Term: CONSERVATION of natural resources; Subject Term: AGRICULTURAL conservation; Subject Term: FARM management; Subject Term: POLLUTION management; Author-Supplied Keyword: Agricultural conservation planning framework; Author-Supplied Keyword: Diffusion; Author-Supplied Keyword: Innovations; Author-Supplied Keyword: Organizational readiness; Author-Supplied Keyword: Semi-structured interviews; Author-Supplied Keyword: Watershed assessment; NAICS/Industry Codes: 417110 Farm, lawn and garden machinery and equipment merchant wholesalers; NAICS/Industry Codes: 333110 Agricultural implement manufacturing; NAICS/Industry Codes: 924120 Administration of Conservation Programs; NAICS/Industry Codes: 115116 Farm Management Services; NAICS/Industry Codes: 115110 Support activities for crop production; Number of Pages: 1p; Document Type: Article | RAYYAN-INCLUSION: {"Philip"=>"Excluded", "Sarah"=>"Included"} | R77: 10.1016/j.jhydrol.2022.127584 | S77: eppi-reviewer;AGRICULTURAL implement;NONPOINT;ource pollution CONSERVATION of natural re;ource;AGRICULTURAL con;ervation FARM management POLLUTION management Agricultural con;ervation planning framework Diffu;ion Innovation;Organizational readine;Semi-;tructured interview;Water;hed a;e;ment
A78: rayyan-83177651 | B78: Understanding the use of decision support tools by conservation professionals and their education and training needs: An application of the Reasoned Action Approach | C78: 2020 | F78: Journal of Soil & Water Conservation | H78: 75 | I78: 3 | J78: 387-399 | K78: Ranjan P and Duriancik L F and Moriasi D N and Carlson D and Anderson K and Prokopy L S | L78: http://0-search.ebscohost.com.catalogue.libraries.london.ac.uk/login.aspx?direct=true&db=a9h&AN=143468930&site=ehost-live | Q78: Ranjan, P. 1 Duriancik, L. F. 2 Moriasi, D. N. 3 Carlson, D. 4 Anderson, K. 5 Prokopy, L. S. 6; Affiliation: 1: Postdoctoral research associate, Department of Forestry and Natural Resources, Purdue University, West Lafayette, Indiana 2: Conservation Effects Assessment Project (CEAP) Watershed assessment studies component leader, USDA Natural Resources Conservation Service (NRCS) Resource Inventory and Assessment Division, Outcomes Team, Beltsville, Maryland 3: Research hydrologist, USDA Agricultural Research Service (ARS) Grazinglands Research Laboratory, El Reno, Oklahoma 4: Conservation initiative coordinator (Mississippi River Basin Initiative, National Water Quality Initiative), USDA NRCS, Washington, DC 5: National water quality and quantity team leader, USDA NRCS, Portland, Oregon 6: Professor, Department of Forestry and Natural Resources, Purdue University, West Lafayette, Indiana; Source Info: May/Jun2020, Vol. 75 Issue 3, p387; Subject Term: TRAINING needs; Subject Term: STAKEHOLDER theory; Subject Term: GOVERNMENT aid; Subject Term: KNOWLEDGE gap theory; Subject Term: WATERSHEDS; Author-Supplied Keyword: Conservation Effects Assessment Project (CEAP); Author-Supplied Keyword: conservation planning; Author-Supplied Keyword: stakeholder engagement; Author-Supplied Keyword: survey; Author-Supplied Keyword: technical roles; Author-Supplied Keyword: watershed assessment; Number of Pages: 13p; Document Type: Article | RAYYAN-INCLUSION: {"Sarah"=>"Included"} | R78: 10.2489/jswc.75.3.387 | S78: eppi-reviewer;TRAINING need;STAKEHOLDER theory GOVERNMENT aid KNOWLEDGE gap theory WATERSHEDS Con;ervation Effect;A;e;ment Project (CEAP) con;ervation planning;takeholder engagement;urvey technical role;water;hed a;ment
A79: rayyan-83177652 | B79: Stakeholder perceptions of scientific knowledge in policy processes: A Peruvian case-study of forestry policy development | C79: 2019 | F79: Science & Public Policy (SPP) | H79: 46 | I79: 4 | J79: 504-517 | K79: Ramirez Luisa F and Belcher Brian M | L79: http://0-search.ebscohost.com.catalogue.libraries.london.ac.uk/login.aspx?direct=true&db=a9h&AN=138277323&site=ehost-live | Q79: Ramirez, Luisa F 1; Email Address: rami9920@mylaurier.ca Belcher, Brian M 1; Affiliation: 1: Sustainability Research Effectiveness Program, College of Interdisciplinary Studies, Royal Roads University, Victoria, Canada; Source Info: Aug2019, Vol. 46 Issue 4, p504; Subject Term: SCIENTIFIC knowledge; Subject Term: SENSORY perception; Subject Term: FORESTS &amp; forestry; Subject Term: DECISION making; Subject Term: DESIGN research; Subject Term: DEVELOPING countries; Author-Supplied Keyword: knowledge-policy models; Author-Supplied Keyword: reseach influence in decision-making; Author-Supplied Keyword: science-policy interface; Author-Supplied Keyword: stakeholders perceptions of research; Number of Pages: 14p; Document Type: Article | RAYYAN-INCLUSION: {"Iris"=>"Maybe"} | R79: 10.1093/scipol/scz003 | S79: eppi-reviewer;SCIENTIFIC knowledge SENSORY perception FORESTS & fore;try DECISION making DESIGN re;earch DEVELOPING countrie;knowledge-policy model;re;each influence in deci;ion-making;cience-policy interface;takeholder;perception;of re;earch
A80: rayyan-83177656 | B80: Advocacy Coalitions and Knowledge Transfer within Geothermal Policy Change in Indonesian Conservation Forests | C80: 2022 | F80: Journal of Environment & Development | H80: 31 | I80: 2 | J80: 168-195 | K80: Pratiwi Santi and Juerges Nataly | L80: http://0-search.ebscohost.com.catalogue.libraries.london.ac.uk/login.aspx?direct=true&db=a9h&AN=156728562&site=ehost-live | Q80: Pratiwi, Santi 1,2; Email Address: spratiw@gwdg.de Juerges, Nataly 1; Affiliation: 1: Chair Group of Forest and Nature Conservation Policy, Georg-August-University GÃ¶ttingen, GÃ¶ttingen, Germany 2: Central Java Nature Conservation Office, Ministry of Environment and Forestry, Indonesia; Source Info: Jun2022, Vol. 31 Issue 2, p168; Subject Term: FOREST conservation; Subject Term: GEOTHERMAL ecology; Subject Term: KNOWLEDGE transfer; Subject Term: GEOTHERMAL resources; Subject Term: FOREST management; Subject Term: FOREST policy; Author-Supplied Keyword: actor analysis; Author-Supplied Keyword: advocacy coalitions; Author-Supplied Keyword: conservation forests; Author-Supplied Keyword: geothermal project; Author-Supplied Keyword: policy change; Author-Supplied Keyword: scientific knowledge transfer; NAICS/Industry Codes: 115310 Support Activities for Forestry; NAICS/Industry Codes: 221116 Geothermal Electric Power Generation; NAICS/Industry Codes: 221330 Steam and Air-Conditioning Supply; Number of Pages: 28p; Document Type: Article | RAYYAN-INCLUSION: {"Alec"=>"Excluded"} | R80: 10.1177/10704965211070244 | S80: eppi-reviewer;FOREST con;ervation GEOTHERMAL ecology KNOWLEDGE tran;fer GEOTHERMAL re;ource;FOREST management FOREST policy actor analy;i;advocacy coalition;con;ervation fore;t;geothermal project policy change;cientific knowledge tran;fer
A81: rayyan-83177658 | B81: Evaluating the impacts of boundary-spanning activities at the interface of environmental science and policy: A review of progress and future research needs | C81: 2019 | F81: Environmental Science and Policy | H81: 92 | J81: 141-151 | K81: Posner S M and Cvitanovic C | L81: https://ovidsp.ovid.com/ovidweb.cgi?T=JS&CSC=Y&NEWS=N&PAGE=fulltext&D=emed20&AN=2001358967 https://discover.lshtm.ac.uk/openurl/44HYG/44HYG_services_page?sid=OVID:embase&id=doi:10.1016%2Fj.envsci.2018.11.006&id=pmid&issn=1462-9011&isbn=&volume=92&issue=&spage=141&pages=141-151&date=2019&title=Environmental+Science+and+Policy&atitle=Evaluating+the+impacts+of+boundary-spanning+activities+at+the+interface+of+environmental+science+and+policy%3A+A+review+of+progress+and+future+research+needs&aulast= | Q81: RAYYAN-INCLUSION: {"Philip"=>"Excluded"} | S81: eppi-reviewer
A82: rayyan-83177663 | B82: Improving ESE policy through research-practice partnerships: Reflections and analysis from New York City | C82: 2021 | F82: Environmental Education Research | H82: 27 | I82: 4 | J82: 595-613 | K82: Pizmony-Levy Oren and McDermott Meredith and Copeland Thaddeus T | L82: https://ovidsp.ovid.com/ovidweb.cgi?T=JS&CSC=Y&NEWS=N&PAGE=fulltext&D=psyc18&AN=2021-42812-009 https://discover.lshtm.ac.uk/openurl/44HYG/44HYG_services_page?sid=OVID:psycdb&id=doi:10.1080%2F13504622.2021.1890696&id=pmid&issn=1350-4622&isbn=&volume=27&issue=4&spage=595&pages=595-613&date=2021&title=Environmental+Education+Research&atitle=Improving+ESE+policy+through+research-practice+partnerships%3A+Reflections+and+analysis+from+New+York+City.&aulast=Pizmony-Levy&pid=%3Cauthor%3EPizmony-Levy%2C | Q82: RAYYAN-INCLUSION: {"Elina"=>"Excluded"} | S82: eppi-reviewer
A83: rayyan-83177669 | B83: Using visual products derived from community research to inform natural resource management policy | C83: 2012 | F83: Land Use Policy | G83: 0264-8377 | H83: 29 | I83: 1 | J83: 46296 | K83: Petheram L and Stacey N and Campbell B M and High C | L83: <Go to ISI>://WOS:000296041300001 | Q83: Petheram, Lisa Stacey, Natasha Campbell, Bruce M. High, Chris Campbell, Bruce/ABF-5579-2020; Stacey, Natasha/N-2225-2013 Stacey, Natasha/0000-0002-2262-9817 1873-5754 | RAYYAN-INCLUSION: {"Philip"=>"Included", "Nibedita"=>"Excluded", "Isobel"=>"Excluded"} | R83: 10.1016/j.landusepol.2011.04.002 | S83: eppi-reviewer
A84: rayyan-83177670 | B84: Identifying climate risk perceptions, information needs, and barriers to information exchange among public land managers | C84: 2018 | F84: Science of the Total Environment | H84: 616 | J84: 245-254 | K84: Peters Casey B and Schwartz Mark W and Lubell Mark N | L84: http://0-search.ebscohost.com.catalogue.libraries.london.ac.uk/login.aspx?direct=true&db=a9h&AN=126994073&site=ehost-live | Q84: Peters, Casey B. 1,2 Schwartz, Mark W. 1,3; Email Address: mwschwartz@ucdavis.edu Lubell, Mark N. 1,4; Affiliation: 1: Department of Environmental Science and Policy, University of California, Davis, CA 95616, USA 2: Graduate Group in Ecology, University of California, Davis, CA 95616, USA 3: John Muir Institute of the Environment, University of California, Davis, CA 95616, USA 4: Center for Environmental Policy and Behavior, University of California, Davis, CA 95616, USA; Source Info: Mar2018, Vol. 616/617, p245; Subject Term: CLIMATE change; Subject Term: INFORMATION sharing; Subject Term: PUBLIC land management; Subject Term: ECOSYSTEM management; Subject Term: LEADERSHIP; Subject Term: ENVIRONMENTAL protection planning; Author-Supplied Keyword: Adaptation; Author-Supplied Keyword: Attitudes; Author-Supplied Keyword: Climate change; Author-Supplied Keyword: Federal agency; Author-Supplied Keyword: Resource management; Author-Supplied Keyword: Risk; NAICS/Industry Codes: 924120 Administration of Conservation Programs; Number of Pages: 10p; Document Type: Article | RAYYAN-INCLUSION: {"Prishnee"=>"Included", "Iris"=>"Included"} | R84: 10.1016/j.scitotenv.2017.11.015 | S84: eppi-reviewer;CLIMATE change INFORMATION;haring PUBLIC land management ECOSYSTEM management LEADERSHIP ENVIRONMENTAL protection planning A...;Federal agency Re;ource management Ri;k
A85: rayyan-83177671 | B85: Science, precaution and innovation for sustainable fisheries: The judgement by the Court of Justice of the EU regarding the electric pulse fishing ban | C85: 2022 | F85: Marine Policy | G85: 0308-597X | H85: 135 | K85: Penca J | L85: <Go to ISI>://WOS:000744255500003 | Q85: Penca, Jerneja 1872-9460 | RAYYAN-INCLUSION: {"Tabitha"=>"Excluded"} | R85: 10.1016/j.marpol.2021.104864 | S85: eppi-reviewer
A86: rayyan-83177673 | B86: Seeds of change? Seed transfer governance in British Columbia: insights from history | C86: 2021 | F86: Canadian Journal of Forest Research | H86: 51 | I86: 2 | J86: 326-338 | K86: Pelai Ricardo and Hagerman Shannon M and Kozak Robert | L86: http://0-search.ebscohost.com.catalogue.libraries.london.ac.uk/login.aspx?direct=true&db=a9h&AN=148820612&site=ehost-live | Q86: Pelai, Ricardo 1; Email Address: ricardo.pelai@alumni.ubc.ca Hagerman, Shannon M. 1 Kozak, Robert 1; Affiliation: 1: Faculty of Forestry, University of British Columbia, 2424 Main Mall, Vancouver, BC V6T 1Z4, Canada.; Source Info: 2021, Vol. 51 Issue 2, p326; Subject Term: SEEDS; Subject Term: FORESTS &amp; forestry; Subject Term: FOREST productivity; Subject Term: FOREST policy; Subject Term: BRITISH Columbia; NAICS/Industry Codes: 115310 Support Activities for Forestry; NAICS/Industry Codes: 411190 Other farm product merchant wholesalers; NAICS/Industry Codes: 418320 Seed merchant wholesalers; NAICS/Industry Codes: 424910 Farm Supplies Merchant Wholesalers; Number of Pages: 13p; Document Type: Article | RAYYAN-INCLUSION: {"Alice"=>"Excluded"} | R86: 10.1139/cjfr-2020-0235 | S86: eppi-reviewer;SEEDS FORESTS & fore;try FOREST productivity FOREST policy BRITISH Columbia
A87: rayyan-83177688 | B87: Principles for evaluating knowledge co-production in natural resource management: Incorporating decision-maker values | C87: 2019 | F87: Journal of Environmental Management | H87: 249 | J87: 109392-109392 | K87: O'Connor R A and Nel J L and Roux D J and Lim-Camacho L and van Kerkhoff L and Leach J | L87: https://ovidsp.ovid.com/ovidweb.cgi?T=JS&CSC=Y&NEWS=N&PAGE=fulltext&D=med16&AN=31446123 https://discover.lshtm.ac.uk/openurl/44HYG/44HYG_services_page?sid=OVID:medline&id=doi:10.1016%2Fj.jenvman.2019.109392&id=pmid31446123&issn=0301-4797&isbn=&volume=249&issue=&spage=109392&pages=109392&date=2019&title=Journal+of+Environmental+Management&atitle=Principles+for+evaluating+knowledge+co-production+in+natural+resource+management%3A+Incorporating+decision-maker+values.&aulast=O%27Connor&pid=%3Cauthor% | O87: O'Connor, Ruth A. Climate Change Institute, The Australian National University, Canberra, Australia; | Q87: O'Connor, Ruth A Nel, Jeanne L Roux, Dirk J Lim-Camacho, Lilly van Kerkhoff, Lorrae Leach, Joan | RAYYAN-INCLUSION: {"Alec"=>"Included"} | S87: eppi-reviewer
A88: rayyan-83177692 | B88: What drives the use of scientific evidence in decision making? The case of the South African Working for Water program | C88: 2015 | F88: Biological Conservation | H88: 184 | J88: 136-144 | K88: Ntshotsho Phumza and Prozesky Heidi E and Esler Karen J and Reyers Belinda | L88: http://0-search.ebscohost.com.catalogue.libraries.london.ac.uk/login.aspx?direct=true&db=a9h&AN=101925211&site=ehost-live | Q88: Ntshotsho, Phumza 1; Email Address: pntshotsho@csir.co.za Prozesky, Heidi E. 2; Email Address: hep@sun.ac.za Esler, Karen J. 3; Email Address: kje@sun.ac.za Reyers, Belinda 1; Email Address: breyers@csir.co.za; Affiliation: 1: Natural Resources and the Environment, CSIR, P.O. Box 320, Stellenbosch 7599, South Africa 2: Department of Sociology &amp; Social Anthropology and Centre for Invasion Biology, Stellenbosch University, Private Bag x1, Matieland 7602, South Africa 3: Department of Conservation Ecology &amp; Entomology and Centre for Invasion Biology, Stellenbosch University, Private Bag x1, Matieland 7602, South Africa; Source Info: Apr2015, Vol. 184, p136; Subject Term: SOCIAL context; Subject Term: INTRODUCED organisms; Subject Term: EVIDENCE-based management; Subject Term: NATURAL resources; Subject Term: DECISION making in science; Subject Term: SOUTH Africa; Author-Supplied Keyword: Invasive alien plant management; Author-Supplied Keyword: Research-implementation gap; Author-Supplied Keyword: Science-based decision making; Author-Supplied Keyword: Social context; Number of Pages: 9p; Document Type: Article | RAYYAN-INCLUSION: {"Isobel"=>"Included"} | R88: 10.1016/j.biocon.2015.01.021 | S88: eppi-reviewer;SOCIAL context INTRODUCED organi;m;EVIDENCE-ba;ed management NATURAL re;ource;DECISION making in;cience SOUTH Africa Inva;ive alien plant management Re;earch-implementation gap Science-ba;ed deci;ion making
A89: rayyan-83177700 | B89: Inclusive, Cross-Sectoral and Evidence-Based Decision-Making for Resilience Planning and Decision-Making in a Devolved Context | C89: 2021 | F89: European Journal of Development Research | H89: 33 | I89: 4 | J89: 1115-1140 | K89: Neely C L and Bourne M and Chesterman S and VÃ¥gen T G and Lekaram V and Winowiecki L A and Prabhu R | L89: http://0-search.ebscohost.com.catalogue.libraries.london.ac.uk/login.aspx?direct=true&db=a9h&AN=151304494&site=ehost-live | Q89: Neely, C. L. 1; Email Address: c.neely@cgiar.org Bourne, M. 1 Chesterman, S. 1 VÃ¥gen, T.-G. 1 Lekaram, V. 2 Winowiecki, L. A. 1 Prabhu, R. 1; Affiliation: 1: World Agroforestry Centre (ICRAF), P.O. Box 30677, Gigiri, 00100, Nairobi, Kenya 2: Department of Finance and Economic Planning, Turkana County Government, P.O. Box 11-30500, Lodwar, Kenya; Source Info: Aug2021, Vol. 33 Issue 4, p1115; Subject Term: DECISION making; Subject Term: ORGANIZATIONAL learning; Subject Term: TECHNICAL assistance; Subject Term: ORGANIZATIONAL change; Subject Term: SUSTAINABILITY; Subject Term: KENYA; Author-Supplied Keyword: Collaboration; Author-Supplied Keyword: Decentralisation; Author-Supplied Keyword: Stakeholder engagement; Number of Pages: 26p; Document Type: Article; Full Text Word Count: 9993 | RAYYAN-INCLUSION: {"Isobel"=>"Excluded"} | R89: 10.1057/s41287-021-00410-3 | S89: eppi-reviewer;DECISION making ORGANIZATIONAL learning TECHNICAL a;i;tance ORGANIZATIONAL change SUSTAINABILITY KENYA Collaboration Decentrali;ation Stakeholder engagement
A90: rayyan-83177702 | B90: Integrating evidence of land use and land cover change for land management policy formulation along the Kenya-Tanzania borderlands | C90: 2019 | F90: Anthropocene | G90: 2213-3054 | H90: 28 | K90: Mustaphi C J. C and Capitani C and Boles O and Kariuki R and Newman R and Munishi L and Marchant R and Lane P | L90: <Go to ISI>://WOS:000500301900005 | Q90: Mustaphi, Colin J. Courtney Capitani, Claudia Boles, Oliver Kariuki, Rebecca Newman, Rebecca Munishi, Linus Marchant, Rob Lane, Paul Lane, Paul/AAK-1995-2020 Lane, Paul/0000-0002-9936-1310; Courtney Mustaphi, Colin/0000-0002-4439-2590 | RAYYAN-INCLUSION: {"Sarah"=>"Excluded"} | R90: 10.1016/j.ancene.2019.100228 | S90: eppi-reviewer
A91: rayyan-83177705 | B91: Diversifying knowledge governance for climate adaptation in protected areas in Colombia | C91: 2019 | F91: Environmental Science and Policy | H91: 94 | J91: 39-48 | K91: Munera C and van Kerkhoff L | L91: https://ovidsp.ovid.com/ovidweb.cgi?T=JS&CSC=Y&NEWS=N&PAGE=fulltext&D=emed20&AN=2001460219 https://discover.lshtm.ac.uk/openurl/44HYG/44HYG_services_page?sid=OVID:embase&id=doi:10.1016%2Fj.envsci.2019.01.004&id=pmid&issn=1462-9011&isbn=&volume=94&issue=&spage=39&pages=39-48&date=2019&title=Environmental+Science+and+Policy&atitle=Diversifying+knowledge+governance+for+climate+adaptation+in+protected+areas+in+Colombia&aulast=Munera&pid=%3Cauthor%3EMunera+C.%3Bvan+Kerkhoff+L.%3C%2Fauthor%3E%3CAN%3E | Q91: RAYYAN-INCLUSION: {"Iris"=>"Included"} | S91: eppi-reviewer
A92: rayyan-83177706 | B92: Champions as Influencers of Science uptake into australian coastal zone policy | C92: 2014 | F92: Coastal Management | G92: 0892-0753 | H92: 42 | I92: 6 | J92: 495-511 | K92: Mumford T and Harvey N | L92: <Go to ISI>://WOS:000343986800001 | Q92: Mumford, Taryn Harvey, Nick 1521-0421 | RAYYAN-INCLUSION: {"Philip"=>"Included", "Tabitha"=>"Excluded", "Prishnee"=>"Included", "Valentin"=>"Included", "fereshteh"=>"Excluded", "Aidan"=>"Maybe", "Nibedita"=>"Included", "Isobel"=>"Excluded"} | R92: 10.1080/08920753.2014.964654 | S92: eppi-reviewer
A93: rayyan-83177712 | B93: Prescribed Burns in California: A Historical Case Study of the Integration of Scientific Research and Policy | C93: 2020 | F93: Fire-Switzerland | G93: 2571-6255 | H93: 3 | I93: 3 | K93: Miller R | L93: <Go to ISI>://WOS:000697569800019 | Q93: Miller, Rebecca | RAYYAN-INCLUSION: {"Alice"=>"Excluded"} | R93: 10.3390/fire3030044 | S93: eppi-reviewer
A94: rayyan-83177713 | B94: Using systematic reviews to inform environmental policy-making | C94: 2022 | F94: Evaluation | H94: 28 | I94: 2 | J94: 210-230 | K94: Miljand Matilda and Eckerberg Katarina | L94: http://0-search.ebscohost.com.catalogue.libraries.london.ac.uk/login.aspx?direct=true&db=a9h&AN=156728489&site=ehost-live | Q94: Miljand, Matilda 1; Email Address: matilda.miljand@statsvet.su.se Eckerberg, Katarina 2; Affiliation: 1: Stockholm University, Sweden 2: UmeÃ¥ University, Sweden; Source Info: Apr2022, Vol. 28 Issue 2, p210; Subject Term: SYSTEMATIC reviews; Subject Term: ENVIRONMENTAL policy; Subject Term: POLICY sciences; Subject Term: SCIENTIFIC knowledge; Subject Term: EVIDENCE-based management; Subject Term: ENVIRONMENTAL management; Author-Supplied Keyword: decision making; Author-Supplied Keyword: evaluation; Author-Supplied Keyword: evidence-based environmental policy; Author-Supplied Keyword: knowledge use; Author-Supplied Keyword: stakeholder involvement; Author-Supplied Keyword: systematic review; NAICS/Industry Codes: 912910 Other provincial and territorial public administration; NAICS/Industry Codes: 924110 Administration of Air and Water Resource and Solid Waste Management Programs; Number of Pages: 21p; Document Type: Article | RAYYAN-INCLUSION: {"Philip"=>"Included", "Nibedita"=>"Included"} | R94: 10.1177/13563890221076540 | S94: eppi-reviewer;SYSTEMATIC review;ENVIRONMENTAL policy POLICY;cience;SCIENTIFIC knowledge EVIDENCE-ba;ed management ENVIRONMENTAL management deci;ion making evaluation evidence-ba;ed environmental policy knowledge u;e;takeholder involvement;y;tematic review
A95: rayyan-83177721 | B95: Facilitating knowledge transfer between researchers and wildfire practitioners about trust: An international case study | C95: 2016 | F95: Forestry Chronicle | G95: 0015-7546 | H95: 92 | I95: 2 | J95: 167-171 | K95: McGee T K and Curtis A and McFarlane B L and Shindler B and Christianson A and Olsen C and McCaffrey S | L95: <Go to ISI>://WOS:000383983100014 | Q95: Mcgee, Tara K. Curtis, Allan McFarlane, Bonita L. Shindler, Bruce Christianson, Amy Olsen, Christine McCaffrey, Sarah McGee, Tara/0000-0003-2234-8879 1499-9315 | RAYYAN-INCLUSION: {"Iris"=>"Excluded"} | R95: 10.5558/tfc2016-035 | S95: eppi-reviewer
A96: rayyan-83177726 | B96: Effective risk governance for environmental policy making: A knowledge management perspective | C96: 2014 | F96: Environmental Science and Policy | H96: 41 | J96: 23-32 | K96: Mauelshagen C and Smith M and Schiller F and Denyer D and Rocks S and Pollard S | L96: https://ovidsp.ovid.com/ovidweb.cgi?T=JS&CSC=Y&NEWS=N&PAGE=fulltext&D=emed15&AN=373163882 https://discover.lshtm.ac.uk/openurl/44HYG/44HYG_services_page?sid=OVID:embase&id=doi:10.1016%2Fj.envsci.2014.04.014&id=pmid&issn=1462-9011&isbn=&volume=41&issue=&spage=23&pages=23-32&date=2014&title=Environmental+Science+and+Policy&atitle=Effective+risk+governance+for+environmental+policy+making%3A+A+knowledge+management+perspective&aulast=Mauelshagen&pid=%3Cauthor%3EMauelshagen+C.%3BSmith+M.%3BSchiller+F | Q96: RAYYAN-INCLUSION: {"Philip"=>"Excluded", "Prishnee"=>"Included"} | S96: eppi-reviewer
A97: rayyan-83177733 | B97: Public managers as catalysts of knowledge co-production? Investigating knowledge dynamics in local environmental policy | C97: 2013 | F97: Environmental Science & Policy | G97: 1462-9011 | H97: 27 | J97: 141-150 | K97: Maiello A and Viegas C V and Frey M and Ribeiro J L. D | L97: <Go to ISI>://WOS:000316843500013 | Q97: Maiello, Antonella Viegas, Claudia V. Frey, Marco Ribeiro, Jose Luis D. Ribeiro, Jose Luis/AAS-9382-2021; Ribeiro, Jose Luis Duarte/I-4276-2016 Ribeiro, Jose Luis/0000-0002-5795-4468; Ribeiro, Jose Luis Duarte/0000-0002-5795-4468 1873-6416 | RAYYAN-INCLUSION: {"Iris"=>"Excluded"} | R97: 10.1016/j.envsci.2012.12.007 | S97: eppi-reviewer
A98: rayyan-83177734 | B98: Scoping Science-Policy Arenas for Regional Ocean Governance in the Wider Caribbean Region | C98: 2021 | F98: Frontiers in Marine Science | H98: 8 | K98: Mahon R and Fanning L | L98: <Go to ISI>://WOS:000674638200001 | Q98: Mahon, Robin Fanning, Lucia 2296-7745 | RAYYAN-INCLUSION: {"Tabitha"=>"Excluded"} | R98: 10.3389/fmars.2021.685122 | S98: eppi-reviewer
A99: rayyan-83177749 | B99: It Is a Balancing Act: The Interface of Scientific Evidence and Policy in Support of Effective Marine Environmental Management | C99: 2022 | F99: Sustainability | H99: 14 | I99: 3 | K99: Lonsdale J A and Gill A B and Alliji K and Birchenough S N. R and Blake S and Buckley H and Clarke C and Clarke S and Edmonds N and Fonseca L and Goodsir F and Griffith A and Judd A and Mulholland R and Perry J and Randall K and Wood D | L99: <Go to ISI>://WOS:000757381000001 | Q99: Lonsdale, Jemma-Anne Gill, Andrew B. Alliji, Khatija Birchenough, Silvana N. R. Blake, Sylvia Buckley, Holly Clarke, Charlotte Clarke, Stacey Edmonds, Nathan Fonseca, Leila Goodsir, Freya Griffith, Andrew Judd, Adrian Mulholland, Rachel Perry, Joe Randall, Karema Wood, Daniel Clarke, Stacey/0000-0003-0332-3959 2071-1050 | RAYYAN-INCLUSION: {"Elina"=>"Excluded", "Iris"=>"Included"} | R99: 10.3390/su14031650 | S99: eppi-reviewer
A100: rayyan-83177752 | B100: 25 Years of Criteria and Indicators for Sustainable Forest Management: How Intergovernmental C&I Processes Have Made a Difference | C100: 2018 | F100: Forests | H100: 9 | I100: 9 | K100: Linser S and Wolfslehner B and Bridge S R. J and Gritten D and Johnson S and Payn T and Prins K and Rasi R and Robertson G | L100: <Go to ISI>://WOS:000448398100074 | Q100: Linser, Stefanie Wolfslehner, Bernhard Bridge, Simon R. J. Gritten, David Johnson, Steven Payn, Tim Prins, Kit Rasi, Rastislav Robertson, Guy Linser, Stefanie/AAF-1589-2020 Bridge, Simon/0000-0002-0717-8579; Payn, Tim/0000-0003-2482-6379; Linser, Stefanie/0000-0002-7505-4922 1999-4907 | RAYYAN-INCLUSION: {"Alec"=>"Excluded"} | R100: 10.3390/f9090578 | S100: eppi-reviewer
...

Sheet Sheet1
A1: Rayyan_key | B1: authors | C1: year | D1: title | E1: journal | F1: volume | G1: issue | H1: pages | I1: doi
A2: rayyan-83178000 | B2: =VLOOKUP($A2,articles_2026_01_26!$A$2:$U$737,11,FALSE) -> Barrett Kyle and Rodriguez Shari L | C2: =VLOOKUP($A2,articles_2026_01_26!$A$2:$U$737,3,FALSE) -> 2021 | D2: =VLOOKUP($A2,articles_2026_01_26!$A$2:$U$737,2,FALSE) -> What Sources Are Natural Resource Managers Using to Make Decisions? | E2: =VLOOKUP($A2,articles_2026_01_26!$A$2:$U$737,6,FALSE) -> Journal of Wildlife Management | F2: =VLOOKUP($A2,articles_2026_01_26!$A$2:$U$737,8,FALSE) -> 85 | G2: =VLOOKUP($A2,articles_2026_01_26!$A$2:$U$737,9,FALSE) -> 8 | H2: =VLOOKUP($A2,articles_2026_01_26!$A$2:$U$737,10,FALSE) -> 1543-1553 | I2: =VLOOKUP($A2,articles_2026_01_26!$A$2:$U$737,18,FALSE) -> 10.1002/jwmg.22112
A3: rayyan-83177408 | B3: =VLOOKUP($A3,articles_2026_01_26!$A$2:$U$737,11,FALSE) -> Weiskopf S R and Harmackova Z V and Johnson C G and Londono-Murcia M C and Miller B W and Myers B J. E and Pereira L and Arce-Plata M I and Blanchard J L and Ferrier S and Fulton E A and Harfoot M and Isbell F and Johnson J A and Mori A S and Weng E S and Rosa I M. D | C3: =VLOOKUP($A3,articles_2026_01_26!$A$2:$U$737,3,FALSE) -> 2022 | D3: =VLOOKUP($A3,articles_2026_01_26!$A$2:$U$737,2,FALSE) -> Increasing the uptake of ecological model results in policy decisions to improve biodiversity outcomes | E3: =VLOOKUP($A3,articles_2026_01_26!$A$2:$U$737,6,FALSE) -> Environmental Modelling & Software | F3: =VLOOKUP($A3,articles_2026_01_26!$A$2:$U$737,8,FALSE) -> 149 | G3: =VLOOKUP($A3,articles_2026_01_26!$A$2:$U$737,9,FALSE) -> 0 | H3: =VLOOKUP($A3,articles_2026_01_26!$A$2:$U$737,10,FALSE) -> 0 | I3: =VLOOKUP($A3,articles_2026_01_26!$A$2:$U$737,18,FALSE) -> 10.1016/j.envsoft.2022.105318
A4: rayyan-83177414 | B4: =VLOOKUP($A4,articles_2026_01_26!$A$2:$U$737,11,FALSE) -> Toomey Anne H and Alvaro MarÃ­a Eugenia Copa and Aiello-Lammens Matthew and Loayza Cossio and Oscar and Barlow Jos | C4: =VLOOKUP($A4,articles_2026_01_26!$A$2:$U$737,3,FALSE) -> 2019 | D4: =VLOOKUP($A4,articles_2026_01_26!$A$2:$U$737,2,FALSE) -> A question of dissemination: Assessing the practices and implications of research in tropical landscapes | E4: =VLOOKUP($A4,articles_2026_01_26!$A$2:$U$737,6,FALSE) -> AMBIO - A Journal of the Human Environment | F4: =VLOOKUP($A4,articles_2026_01_26!$A$2:$U$737,8,FALSE) -> 48 | G4: =VLOOKUP($A4,articles_2026_01_26!$A$2:$U$737,9,FALSE) -> 1 | H4: =VLOOKUP($A4,articles_2026_01_26!$A$2:$U$737,10,FALSE) -> 35-47 | I4: =VLOOKUP($A4,articles_2026_01_26!$A$2:$U$737,18,FALSE) -> 10.1007/s13280-018-1056-5
A5: rayyan-83177415 | B5: =VLOOKUP($A5,articles_2026_01_26!$A$2:$U$737,11,FALSE) -> Taylor C and Cockburn J and Rouget M and Ray-Mukherjee J and Mukherjee S and Slotow R and Roberts D and Boon R and O'Donoghue S and Douwes E | C5: =VLOOKUP($A5,articles_2026_01_26!$A$2:$U$737,3,FALSE) -> 2016 | D5: =VLOOKUP($A5,articles_2026_01_26!$A$2:$U$737,2,FALSE) -> lEvaluating the outcomes and processes of a research-action partnership: The need for continuous reflective evaluation | E5: =VLOOKUP($A5,articles_2026_01_26!$A$2:$U$737,6,FALSE) -> Bothalia | F5: =VLOOKUP($A5,articles_2026_01_26!$A$2:$U$737,8,FALSE) -> 46 | G5: =VLOOKUP($A5,articles_2026_01_26!$A$2:$U$737,9,FALSE) -> 2 | H5: =VLOOKUP($A5,articles_2026_01_26!$A$2:$U$737,10,FALSE) -> 0 | I5: =VLOOKUP($A5,articles_2026_01_26!$A$2:$U$737,18,FALSE) -> 10.4102/abc.v46i2.2154
A6: rayyan-83177416 | B6: =VLOOKUP($A6,articles_2026_01_26!$A$2:$U$737,11,FALSE) -> Taft Heather R and McCoskey Dana N and Miller Joshua M and Pearson Sarah K and Coleman Melinda A and Fletcher Nicholas K and Mittan Cinnamon S and Meek Mariah H and Barbosa Soraia | C6: =VLOOKUP($A6,articles_2026_01_26!$A$2:$U$737,3,FALSE) -> 2020 | D6: =VLOOKUP($A6,articles_2026_01_26!$A$2:$U$737,2,FALSE) -> Researchâ€“management partnerships: An opportunity to integrate genetics in conservation actions | E6: =VLOOKUP($A6,articles_2026_01_26!$A$2:$U$737,6,FALSE) -> Conservation Science & Practice | F6: =VLOOKUP($A6,articles_2026_01_26!$A$2:$U$737,8,FALSE) -> 2 | G6: =VLOOKUP($A6,articles_2026_01_26!$A$2:$U$737,9,FALSE) -> 9 | H6: =VLOOKUP($A6,articles_2026_01_26!$A$2:$U$737,10,FALSE) -> 46235 | I6: =VLOOKUP($A6,articles_2026_01_26!$A$2:$U$737,18,FALSE) -> 10.1111/csp2.218
A7: rayyan-83177418 | B7: =VLOOKUP($A7,articles_2026_01_26!$A$2:$U$737,11,FALSE) -> Suskevics M and Raadom T and Vanem B and Kana S and Roasto R and Runnel V and Kulvik M | C7: =VLOOKUP($A7,articles_2026_01_26!$A$2:$U$737,3,FALSE) -> 2021 | D7: =VLOOKUP($A7,articles_2026_01_26!$A$2:$U$737,2,FALSE) -> Challenges and opportunities of engaging biodiversity-related citizen science data in environmental decision-making: Practitioners' perceptions and a database analysis from Estonia | E7: =VLOOKUP($A7,articles_2026_01_26!$A$2:$U$737,6,FALSE) -> Journal for Nature Conservation | F7: =VLOOKUP($A7,articles_2026_01_26!$A$2:$U$737,8,FALSE) -> 64 | G7: =VLOOKUP($A7,articles_2026_01_26!$A$2:$U$737,9,FALSE) -> 0 | H7: =VLOOKUP($A7,articles_2026_01_26!$A$2:$U$737,10,FALSE) -> 0 | I7: =VLOOKUP($A7,articles_2026_01_26!$A$2:$U$737,18,FALSE) -> 10.1016/j.jnc.2021.126068
A8: rayyan-83177421 | B8: =VLOOKUP($A8,articles_2026_01_26!$A$2:$U$737,11,FALSE) -> Stephenson P J and Bowles-Newark Nadine and Regan Eugenie and Stanwell-Smith Damon and Diagana MallÃ© and HÃ¶ft Robert and Abarchi Harouna and Abrahamse Tanya and Akello Christine and Allison Hilary and Banki Olaf and Batieno Barthelemy and Dieme Samuel and Domingos Arthur and Galt Russell and Githaiga Cicilia W and Guindo Abdoulaye Bine and Hafashimana David L N and Hirsch Tim and Hobern Donald | C8: =VLOOKUP($A8,articles_2026_01_26!$A$2:$U$737,3,FALSE) -> 2017 | D8: =VLOOKUP($A8,articles_2026_01_26!$A$2:$U$737,2,FALSE) -> Unblocking the flow of biodiversity data for decision-making in Africa | E8: =VLOOKUP($A8,articles_2026_01_26!$A$2:$U$737,6,FALSE) -> Biological Conservation | F8: =VLOOKUP($A8,articles_2026_01_26!$A$2:$U$737,8,FALSE) -> 213 | G8: =VLOOKUP($A8,articles_2026_01_26!$A$2:$U$737,9,FALSE) -> 0 | H8: =VLOOKUP($A8,articles_2026_01_26!$A$2:$U$737,10,FALSE) -> 335-340 | I8: =VLOOKUP($A8,articles_2026_01_26!$A$2:$U$737,18,FALSE) -> 10.1016/j.biocon.2016.09.003
A9: rayyan-83177422 | B9: =VLOOKUP($A9,articles_2026_01_26!$A$2:$U$737,11,FALSE) -> Sitas N and Harmackova Z V and Anticamara J A and Arneth A and Badola R and Biggs R and Blanchard R and Brotons L and Cantele M and Coetzer K and DasGupta R and den Belder E and Ghosh S and Guisan A and Gundimeda H and Hamann M and Harrison P A and Hashimoto S and Hauck J and Klatt B J and Kok K and Krug R M and Niamir A and O'Farrell P J and Okayasu S and Palomo I and Pereira L M and Riordan P and Santos-Martin F and Selomane O and Shin Y J and Valle M | C9: =VLOOKUP($A9,articles_2026_01_26!$A$2:$U$737,3,FALSE) -> 2019 | D9: =VLOOKUP($A9,articles_2026_01_26!$A$2:$U$737,2,FALSE) -> Exploring the usefulness of scenario archetypes in science-policy processes: experience across IPBES assessments | E9: =VLOOKUP($A9,articles_2026_01_26!$A$2:$U$737,6,FALSE) -> Ecology and Society | F9: =VLOOKUP($A9,articles_2026_01_26!$A$2:$U$737,8,FALSE) -> 24 | G9: =VLOOKUP($A9,articles_2026_01_26!$A$2:$U$737,9,FALSE) -> 3 | H9: =VLOOKUP($A9,articles_2026_01_26!$A$2:$U$737,10,FALSE) -> 0 | I9: =VLOOKUP($A9,articles_2026_01_26!$A$2:$U$737,18,FALSE) -> 10.5751/es-11039-240335
A10: rayyan-83177423 | B10: =VLOOKUP($A10,articles_2026_01_26!$A$2:$U$737,11,FALSE) -> Shiffman D S and Macdonald C C and Wallace S S and Dulvy N K | C10: =VLOOKUP($A10,articles_2026_01_26!$A$2:$U$737,3,FALSE) -> 2021 | D10: =VLOOKUP($A10,articles_2026_01_26!$A$2:$U$737,2,FALSE) -> The role and value of science in shark conservation advocacy | E10: =VLOOKUP($A10,articles_2026_01_26!$A$2:$U$737,6,FALSE) -> Scientific Reports | F10: =VLOOKUP($A10,articles_2026_01_26!$A$2:$U$737,8,FALSE) -> 11 | G10: =VLOOKUP($A10,articles_2026_01_26!$A$2:$U$737,9,FALSE) -> 1 | H10: =VLOOKUP($A10,articles_2026_01_26!$A$2:$U$737,10,FALSE) -> 16626-16626 | I10: =VLOOKUP($A10,articles_2026_01_26!$A$2:$U$737,18,FALSE) -> 0
A11: rayyan-83177435 | B11: =VLOOKUP($A11,articles_2026_01_26!$A$2:$U$737,11,FALSE) -> Noble M M and Fulton C J | C11: =VLOOKUP($A11,articles_2026_01_26!$A$2:$U$737,3,FALSE) -> 2020 | D11: =VLOOKUP($A11,articles_2026_01_26!$A$2:$U$737,2,FALSE) -> Pathways to impact for aquatic conservation science via multi-modal communication and stakeholder engagement | E11: =VLOOKUP($A11,articles_2026_01_26!$A$2:$U$737,6,FALSE) -> Aquatic Conservation-Marine and Freshwater Ecosystems | F11: =VLOOKUP($A11,articles_2026_01_26!$A$2:$U$737,8,FALSE) -> 30 | G11: =VLOOKUP($A11,articles_2026_01_26!$A$2:$U$737,9,FALSE) -> 9 | H11: =VLOOKUP($A11,articles_2026_01_26!$A$2:$U$737,10,FALSE) -> 1791-1797 | I11: =VLOOKUP($A11,articles_2026_01_26!$A$2:$U$737,18,FALSE) -> 10.1002/aqc.3380
A12: rayyan-83177440 | B12: =VLOOKUP($A12,articles_2026_01_26!$A$2:$U$737,11,FALSE) -> Martin-Mora E and Ellis S and Page L M | C12: =VLOOKUP($A12,articles_2026_01_26!$A$2:$U$737,3,FALSE) -> 2020 | D12: =VLOOKUP($A12,articles_2026_01_26!$A$2:$U$737,2,FALSE) -> Use of web-based species occurrence information systems by academics and government professionals | E12: =VLOOKUP($A12,articles_2026_01_26!$A$2:$U$737,6,FALSE) -> PLoS ONE [Electronic Resource] | F12: =VLOOKUP($A12,articles_2026_01_26!$A$2:$U$737,8,FALSE) -> 15 | G12: =VLOOKUP($A12,articles_2026_01_26!$A$2:$U$737,9,FALSE) -> 7 | H12: =VLOOKUP($A12,articles_2026_01_26!$A$2:$U$737,10,FALSE) -> e0236556-e0236556 | I12: =VLOOKUP($A12,articles_2026_01_26!$A$2:$U$737,18,FALSE) -> 0
A13: rayyan-83177449 | B13: =VLOOKUP($A13,articles_2026_01_26!$A$2:$U$737,11,FALSE) -> Jacobson C and Lisle A and Carter R W and Hockings M T | C13: =VLOOKUP($A13,articles_2026_01_26!$A$2:$U$737,3,FALSE) -> 2013 | D13: =VLOOKUP($A13,articles_2026_01_26!$A$2:$U$737,2,FALSE) -> Improving technical information use: what can be learnt from a manager's perspective? | E13: =VLOOKUP($A13,articles_2026_01_26!$A$2:$U$737,6,FALSE) -> Environmental Management | F13: =VLOOKUP($A13,articles_2026_01_26!$A$2:$U$737,8,FALSE) -> 52 | G13: =VLOOKUP($A13,articles_2026_01_26!$A$2:$U$737,9,FALSE) -> 1 | H13: =VLOOKUP($A13,articles_2026_01_26!$A$2:$U$737,10,FALSE) -> 221-233 | I13: =VLOOKUP($A13,articles_2026_01_26!$A$2:$U$737,18,FALSE) -> 0
... A170: rayyan-164700304 | B170: =VLOOKUP($A170,articles_2026_01_26!$A$2:$U$737,11,FALSE) -> FerrÃ©, M and Martin-Ortega, J and Di Gregorio, M and Dallimer, M | C170: =VLOOKUP($A170,articles_2026_01_26!$A$2:$U$737,3,FALSE) -> 2022 | D170: =VLOOKUP($A170,articles_2026_01_26!$A$2:$U$737,2,FALSE) -> How do information flows affect impact from environmental research?-An analysis of a science-policy network | E170: =VLOOKUP($A170,articles_2026_01_26!$A$2:$U$737,6,FALSE) -> JOURNAL OF ENVIRONMENTAL MANAGEMENT | F170: =VLOOKUP($A170,articles_2026_01_26!$A$2:$U$737,8,FALSE) -> 321 | G170: =VLOOKUP($A170,articles_2026_01_26!$A$2:$U$737,9,FALSE) -> 0 | H170: =VLOOKUP($A170,articles_2026_01_26!$A$2:$U$737,10,FALSE) -> 0 | I170: =VLOOKUP($A170,articles_2026_01_26!$A$2:$U$737,18,FALSE) -> 10.1016/j.jenvman.2022.115828
